<?xml version="1.0" encoding="utf-8"?>
<session sessioncode="4080950048">
 <general>
  <client_version>22.3.1.15</client_version>
  <mode>real</mode>
  <gametype>Holdem NL €0,25/€0,50</gametype>
  <tablename>100BB Salzburg 14, 488044432</tablename>
  <tablecurrency>EUR</tablecurrency>
  <duration>00:29:11</duration>
  <gamecount>52</gamecount>
  <startdate>2022-08-11 21:54:06</startdate>
  <currency>EUR</currency>
  <nickname>13373678</nickname>
  <bets>€58,81</bets>
  <wins>€36,06</wins>
  <chipsin>€49,50</chipsin>
  <chipsout>€55,27</chipsout>
  <statuspoints>0,00</statuspoints>
  <awardpoints>0,00</awardpoints>
  <ipoints>0,00</ipoints>
  <tablesize>6</tablesize>
 </general>
 <game gamecode="3701893838">
  <general>
   <startdate>2022-08-11 21:54:06</startdate>
   <players>
    <player dealer="0" name="Player 1" seat="1" chips="€66,46" win="€0" bet="€0,50"/>
    <player dealer="0" name="Player 3" seat="3" chips="€51,88" win="€0" bet="€0"/>
    <player dealer="0" name="Player 5" seat="5" chips="€65,53" win="€0" bet="€0"/>
    <player dealer="1" name="Player 6" seat="6" chips="€90,99" win="€0" bet="€0,50"/>
    <player dealer="0" name="Player 10" seat="10" chips="€54,87" win="€1,50" bet="€2,25"/>
   </players>
  </general>
  <round no="0">
   <action type="1" sum="€0,25" player="Player 10" no="1"/>
   <action type="2" sum="€0,50" player="Player 1" no="2"/>
  </round>
  <round no="1">
   <cards type="Pocket" player="Player 3">X X</cards>
   <action type="0" sum="€0" player="Player 3" no="3"/>
   <cards type="Pocket" player="Player 5">X X</cards>
   <action type="0" sum="€0" player="Player 5" no="4"/>
   <cards type="Pocket" player="Player 6">X X</cards>
   <action type="3" sum="€0,50" player="Player 6" no="5"/>
   <cards type="Pocket" player="Player 10">X X</cards>
   <action type="23" sum="€2,25" player="Player 10" no="6"/>
   <cards type="Pocket" player="Player 1">X X</cards>
   <action type="0" sum="€0" player="Player 1" no="7"/>
   <action type="0" sum="€0" player="Player 6" no="8"/>
  </round>
 </game>
 <game gamecode="3701893961">
  <general>
   <startdate>2022-08-11 21:54:56</startdate>
   <players>
    <player dealer="0" name="Player 1" seat="1" chips="€65,96" win="€0" bet="€0,25"/>
    <player dealer="0" name="Player 3" seat="3" chips="€51,88" win="€0" bet="€0,50"/>
    <player dealer="0" name="Player 5" seat="5" chips="€65,53" win="€0" bet="€0"/>
    <player dealer="0" name="Player 6" seat="6" chips="€90,49" win="€0" bet="€0"/>
    <player dealer="1" name="Player 10" seat="10" chips="€55,87" win="€1,25" bet="€1,25"/>
   </players>
  </general>
  <round no="0">
   <action type="1" sum="€0,25" player="Player 1" no="1"/>
   <action type="2" sum="€0,50" player="Player 3" no="2"/>
  </round>
  <round no="1">
   <cards type="Pocket" player="Player 5">X X</cards>
   <action type="0" sum="€0" player="Player 5" no="3"/>
   <cards type="Pocket" player="Player 6">X X</cards>
   <action type="0" sum="€0" player="Player 6" no="4"/>
   <cards type="Pocket" player="Player 10">X X</cards>
   <action type="23" sum="€1,25" player="Player 10" no="5"/>
   <cards type="Pocket" player="Player 1">X X</cards>
   <action type="0" sum="€0" player="Player 1" no="6"/>
   <cards type="Pocket" player="Player 3">X X</cards>
   <action type="0" sum="€0" player="Player 3" no="7"/>
  </round>
 </game>
 <game gamecode="3701894010">
  <general>
   <startdate>2022-08-11 21:55:16</startdate>
   <players>
    <player dealer="1" name="Player 1" seat="1" chips="€65,71" win="€0" bet="€0"/>
    <player dealer="0" name="Player 3" seat="3" chips="€51,38" win="€0" bet="€0,25"/>
    <player dealer="0" name="Player 5" seat="5" chips="€65,53" win="€0,50" bet="€0,50"/>
    <player dealer="0" name="Player 6" seat="6" chips="€90,49" win="€0" bet="€0"/>
    <player dealer="0" name="Player 10" seat="10" chips="€56,62" win="€0" bet="€0"/>
   </players>
  </general>
  <round no="0">
   <action type="1" sum="€0,25" player="Player 3" no="1"/>
   <action type="2" sum="€0,50" player="Player 5" no="2"/>
  </round>
  <round no="1">
   <cards type="Pocket" player="Player 5">X X</cards>
   <cards type="Pocket" player="Player 6">X X</cards>
   <action type="0" sum="€0" player="Player 6" no="3"/>
   <cards type="Pocket" player="Player 10">X X</cards>
   <action type="0" sum="€0" player="Player 10" no="4"/>
   <cards type="Pocket" player="Player 1">X X</cards>
   <action type="0" sum="€0" player="Player 1" no="5"/>
   <cards type="Pocket" player="Player 3">X X</cards>
   <action type="0" sum="€0" player="Player 3" no="6"/>
  </round>
 </game>
 <game gamecode="3701894062">
  <general>
   <startdate>2022-08-11 21:55:35</startdate>
   <players>
    <player dealer="0" name="Player 1" seat="1" chips="€65,71" win="€1,25" bet="€1,22"/>
    <player dealer="1" name="Player 3" seat="3" chips="€51,13" win="€0" bet="€0"/>
    <player dealer="0" name="Player 5" seat="5" chips="€65,78" win="€0" bet="€0,25"/>
    <player dealer="0" name="Player 6" seat="6" chips="€90,49" win="€0" bet="€0,50"/>
    <player dealer="0" name="Player 10" seat="10" chips="€56,62" win="€0" bet="€0"/>
   </players>
  </general>
  <round no="0">
   <action type="1" sum="€0,25" player="Player 5" no="1"/>
   <action type="2" sum="€0,50" player="Player 6" no="2"/>
  </round>
  <round no="1">
   <cards type="Pocket" player="Player 10">X X</cards>
   <action type="0" sum="€0" player="Player 10" no="3"/>
   <cards type="Pocket" player="Player 1">X X</cards>
   <action type="23" sum="€1,22" player="Player 1" no="4"/>
   <cards type="Pocket" player="Player 3">X X</cards>
   <action type="0" sum="€0" player="Player 3" no="5"/>
   <cards type="Pocket" player="Player 5">X X</cards>
   <action type="0" sum="€0" player="Player 5" no="6"/>
   <cards type="Pocket" player="Player 6">X X</cards>
   <action type="0" sum="€0" player="Player 6" no="7"/>
  </round>
 </game>
 <game gamecode="3701894828">
  <general>
   <startdate>2022-08-11 21:55:50</startdate>
   <players>
    <player dealer="0" name="Bierschiss67" seat="1" chips="€66,46" win="€0" bet="€0"/>
    <player dealer="0" name="AlanMeining" seat="3" chips="€51,13" win="€1,25" bet="€1,10"/>
    <player dealer="1" name="Back2Warcraft" seat="5" chips="€65,53" win="€0" bet="€0"/>
    <player dealer="0" name="InMaxBzKillendos" seat="6" chips="€89,99" win="€0" bet="€0,25"/>
    <player dealer="0" name="13373678" seat="8" chips="€50" win="€0" bet="€0,50"/>
    <player dealer="0" name="SteveBiko" seat="10" chips="€56,62" win="€0" bet="€0"/>
   </players>
  </general>
  <round no="0">
   <action type="1" sum="€0,25" player="InMaxBzKillendos" no="1"/>
   <action type="2" sum="€0,50" player="13373678" no="2"/>
  </round>
  <round no="1">
   <cards type="Pocket" player="SteveBiko">X X</cards>
   <action type="0" sum="€0" player="SteveBiko" no="3"/>
   <cards type="Pocket" player="Bierschiss67">X X</cards>
   <action type="0" sum="€0" player="Bierschiss67" no="4"/>
   <cards type="Pocket" player="AlanMeining">X X</cards>
   <action type="23" sum="€1,10" player="AlanMeining" no="5"/>
   <cards type="Pocket" player="Back2Warcraft">X X</cards>
   <action type="0" sum="€0" player="Back2Warcraft" no="6"/>
   <cards type="Pocket" player="InMaxBzKillendos">X X</cards>
   <action type="0" sum="€0" player="InMaxBzKillendos" no="7"/>
   <cards type="Pocket" player="13373678">SK D2</cards>
   <action type="0" sum="€0" player="13373678" no="8"/>
  </round>
 </game>
 <game gamecode="3701894913">
  <general>
   <startdate>2022-08-11 21:56:20</startdate>
   <players>
    <player dealer="0" name="Bierschiss67" seat="1" chips="€66,46" win="€0" bet="€0"/>
    <player dealer="0" name="AlanMeining" seat="3" chips="€51,88" win="€0" bet="€0"/>
    <player dealer="0" name="Back2Warcraft" seat="5" chips="€65,53" win="€0" bet="€0"/>
    <player dealer="1" name="InMaxBzKillendos" seat="6" chips="€89,74" win="€0" bet="€0"/>
    <player dealer="0" name="13373678" seat="8" chips="€50" win="€0" bet="€2,49"/>
    <player dealer="0" name="SteveBiko" seat="10" chips="€56,62" win="€4,83" bet="€4,48"/>
   </players>
  </general>
  <round no="0">
   <action type="1" sum="€0,25" player="13373678" no="1"/>
   <action type="2" sum="€0,50" player="SteveBiko" no="2"/>
  </round>
  <round no="1">
   <cards type="Pocket" player="Bierschiss67">X X</cards>
   <action type="0" sum="€0" player="Bierschiss67" no="3"/>
   <cards type="Pocket" player="AlanMeining">X X</cards>
   <action type="0" sum="€0" player="AlanMeining" no="4"/>
   <cards type="Pocket" player="Back2Warcraft">X X</cards>
   <action type="0" sum="€0" player="Back2Warcraft" no="5"/>
   <cards type="Pocket" player="InMaxBzKillendos">X X</cards>
   <action type="0" sum="€0" player="InMaxBzKillendos" no="6"/>
   <cards type="Pocket" player="13373678">CQ C4</cards>
   <action type="23" sum="€1,50" player="13373678" no="7"/>
   <cards type="Pocket" player="SteveBiko">X X</cards>
   <action type="3" sum="€1" player="SteveBiko" no="8"/>
  </round>
  <round no="2">
   <cards type="Flop">SK DQ C7</cards>
   <action type="4" sum="€0" player="13373678" no="9"/>
   <action type="5" sum="€0,99" player="SteveBiko" no="10"/>
   <action type="3" sum="€0,99" player="13373678" no="11"/>
  </round>
  <round no="3">
   <cards type="Turn">CA</cards>
   <action type="4" sum="€0" player="13373678" no="12"/>
   <action type="4" sum="€0" player="SteveBiko" no="13"/>
  </round>
  <round no="4">
   <cards type="River">H5</cards>
   <action type="4" sum="€0" player="13373678" no="14"/>
   <action type="5" sum="€1,99" player="SteveBiko" no="15"/>
   <action type="0" sum="€0" player="13373678" no="16"/>
  </round>
 </game>
 <game gamecode="3701895087">
  <general>
   <startdate>2022-08-11 21:57:30</startdate>
   <players>
    <player dealer="0" name="Bierschiss67" seat="1" chips="€66,46" win="€0" bet="€1,25"/>
    <player dealer="0" name="AlanMeining" seat="3" chips="€51,88" win="€0" bet="€0"/>
    <player dealer="0" name="Back2Warcraft" seat="5" chips="€65,53" win="€0" bet="€0"/>
    <player dealer="0" name="InMaxBzKillendos" seat="6" chips="€89,74" win="€0" bet="€0"/>
    <player dealer="1" name="13373678" seat="8" chips="€50" win="€2,67" bet="€3,31"/>
    <player dealer="0" name="SteveBiko" seat="10" chips="€58,96" win="€0" bet="€0,25"/>
   </players>
  </general>
  <round no="0">
   <action type="1" sum="€0,25" player="SteveBiko" no="1"/>
   <action type="2" sum="€0,50" player="Bierschiss67" no="2"/>
  </round>
  <round no="1">
   <cards type="Pocket" player="AlanMeining">X X</cards>
   <action type="0" sum="€0" player="AlanMeining" no="3"/>
   <cards type="Pocket" player="Back2Warcraft">X X</cards>
   <action type="0" sum="€0" player="Back2Warcraft" no="4"/>
   <cards type="Pocket" player="InMaxBzKillendos">X X</cards>
   <action type="0" sum="€0" player="InMaxBzKillendos" no="5"/>
   <cards type="Pocket" player="13373678">C9 HA</cards>
   <action type="23" sum="€1,25" player="13373678" no="6"/>
   <cards type="Pocket" player="SteveBiko">X X</cards>
   <action type="0" sum="€0" player="SteveBiko" no="7"/>
   <cards type="Pocket" player="Bierschiss67">X X</cards>
   <action type="3" sum="€0,75" player="Bierschiss67" no="8"/>
  </round>
  <round no="2">
   <cards type="Flop">S3 C7 H2</cards>
   <action type="4" sum="€0" player="Bierschiss67" no="9"/>
   <action type="4" sum="€0" player="13373678" no="10"/>
  </round>
  <round no="3">
   <cards type="Turn">H8</cards>
   <action type="4" sum="€0" player="Bierschiss67" no="11"/>
   <action type="4" sum="€0" player="13373678" no="12"/>
  </round>
  <round no="4">
   <cards type="River">CK</cards>
   <action type="4" sum="€0" player="Bierschiss67" no="13"/>
   <action type="5" sum="€2,06" player="13373678" no="14"/>
   <action type="0" sum="€0" player="Bierschiss67" no="15"/>
  </round>
 </game>
 <game gamecode="3701895215">
  <general>
   <startdate>2022-08-11 21:58:18</startdate>
   <players>
    <player dealer="0" name="Bierschiss67" seat="1" chips="€65,21" win="€0" bet="€0,25"/>
    <player dealer="0" name="AlanMeining" seat="3" chips="€51,88" win="€0" bet="€0,50"/>
    <player dealer="0" name="Back2Warcraft" seat="5" chips="€65,53" win="€0" bet="€0"/>
    <player dealer="0" name="InMaxBzKillendos" seat="6" chips="€89,74" win="€0" bet="€0"/>
    <player dealer="0" name="13373678" seat="8" chips="€51,42" win="€1,25" bet="€1,25"/>
    <player dealer="1" name="SteveBiko" seat="10" chips="€58,71" win="€0" bet="€0"/>
   </players>
  </general>
  <round no="0">
   <action type="1" sum="€0,25" player="Bierschiss67" no="1"/>
   <action type="2" sum="€0,50" player="AlanMeining" no="2"/>
  </round>
  <round no="1">
   <cards type="Pocket" player="Back2Warcraft">X X</cards>
   <action type="0" sum="€0" player="Back2Warcraft" no="3"/>
   <cards type="Pocket" player="InMaxBzKillendos">X X</cards>
   <action type="0" sum="€0" player="InMaxBzKillendos" no="4"/>
   <cards type="Pocket" player="13373678">SQ DQ</cards>
   <action type="23" sum="€1,25" player="13373678" no="5"/>
   <cards type="Pocket" player="SteveBiko">X X</cards>
   <action type="0" sum="€0" player="SteveBiko" no="6"/>
   <cards type="Pocket" player="Bierschiss67">X X</cards>
   <action type="0" sum="€0" player="Bierschiss67" no="7"/>
   <cards type="Pocket" player="AlanMeining">X X</cards>
   <action type="0" sum="€0" player="AlanMeining" no="8"/>
  </round>
 </game>
 <game gamecode="3701895269">
  <general>
   <startdate>2022-08-11 21:58:39</startdate>
   <players>
    <player dealer="1" name="Bierschiss67" seat="1" chips="€64,96" win="€0" bet="€0"/>
    <player dealer="0" name="AlanMeining" seat="3" chips="€51,38" win="€0" bet="€0,25"/>
    <player dealer="0" name="Back2Warcraft" seat="5" chips="€65,53" win="€0" bet="€1,25"/>
    <player dealer="0" name="InMaxBzKillendos" seat="6" chips="€89,74" win="€0" bet="€0"/>
    <player dealer="0" name="13373678" seat="8" chips="€52,17" win="€2,67" bet="€3,31"/>
    <player dealer="0" name="SteveBiko" seat="10" chips="€58,71" win="€0" bet="€0"/>
   </players>
  </general>
  <round no="0">
   <action type="1" sum="€0,25" player="AlanMeining" no="1"/>
   <action type="2" sum="€0,50" player="Back2Warcraft" no="2"/>
  </round>
  <round no="1">
   <cards type="Pocket" player="InMaxBzKillendos">X X</cards>
   <action type="0" sum="€0" player="InMaxBzKillendos" no="3"/>
   <cards type="Pocket" player="13373678">D7 D6</cards>
   <action type="23" sum="€1,25" player="13373678" no="4"/>
   <cards type="Pocket" player="SteveBiko">X X</cards>
   <action type="0" sum="€0" player="SteveBiko" no="5"/>
   <cards type="Pocket" player="Bierschiss67">X X</cards>
   <action type="0" sum="€0" player="Bierschiss67" no="6"/>
   <cards type="Pocket" player="AlanMeining">X X</cards>
   <action type="0" sum="€0" player="AlanMeining" no="7"/>
   <cards type="Pocket" player="Back2Warcraft">X X</cards>
   <action type="3" sum="€0,75" player="Back2Warcraft" no="8"/>
  </round>
  <round no="2">
   <cards type="Flop">HK S9 C7</cards>
   <action type="4" sum="€0" player="Back2Warcraft" no="9"/>
   <action type="5" sum="€2,06" player="13373678" no="10"/>
   <action type="0" sum="€0" player="Back2Warcraft" no="11"/>
  </round>
 </game>
 <game gamecode="3701895359">
  <general>
   <startdate>2022-08-11 21:59:10</startdate>
   <players>
    <player dealer="0" name="Bierschiss67" seat="1" chips="€64,96" win="€0" bet="€20"/>
    <player dealer="1" name="AlanMeining" seat="3" chips="€51,13" win="€0" bet="€0"/>
    <player dealer="0" name="Back2Warcraft" seat="5" chips="€64,28" win="€39,28" bet="€64,28"/>
    <player dealer="0" name="InMaxBzKillendos" seat="6" chips="€89,74" win="€0" bet="€0,50"/>
    <player dealer="0" name="13373678" seat="8" chips="€53,59" win="€0" bet="€0"/>
    <player dealer="0" name="SteveBiko" seat="10" chips="€58,71" win="€0" bet="€0"/>
   </players>
  </general>
  <round no="0">
   <action type="1" sum="€0,25" player="Back2Warcraft" no="1"/>
   <action type="2" sum="€0,50" player="InMaxBzKillendos" no="2"/>
  </round>
  <round no="1">
   <cards type="Pocket" player="13373678">SA C4</cards>
   <action type="0" sum="€0" player="13373678" no="3"/>
   <cards type="Pocket" player="SteveBiko">X X</cards>
   <action type="0" sum="€0" player="SteveBiko" no="4"/>
   <cards type="Pocket" player="Bierschiss67">X X</cards>
   <action type="23" sum="€1,22" player="Bierschiss67" no="5"/>
   <cards type="Pocket" player="AlanMeining">X X</cards>
   <action type="0" sum="€0" player="AlanMeining" no="6"/>
   <cards type="Pocket" player="Back2Warcraft">X X</cards>
   <action type="23" sum="€6" player="Back2Warcraft" no="7"/>
   <cards type="Pocket" player="InMaxBzKillendos">X X</cards>
   <action type="0" sum="€0" player="InMaxBzKillendos" no="8"/>
   <action type="23" sum="€13" player="Bierschiss67" no="9"/>
   <action type="3" sum="€7" player="Back2Warcraft" no="10"/>
  </round>
  <round no="2">
   <cards type="Flop">D10 CQ H4</cards>
   <action type="4" sum="€0" player="Back2Warcraft" no="11"/>
   <action type="5" sum="€7" player="Bierschiss67" no="12"/>
   <action type="3" sum="€7" player="Back2Warcraft" no="13"/>
  </round>
  <round no="3">
   <cards type="Turn">D7</cards>
   <action type="4" sum="€0" player="Back2Warcraft" no="14"/>
   <action type="4" sum="€0" player="Bierschiss67" no="15"/>
  </round>
  <round no="4">
   <cards type="River">C8</cards>
   <action type="5" sum="€44,28" player="Back2Warcraft" no="16"/>
   <action type="0" sum="€0" player="Bierschiss67" no="17"/>
  </round>
 </game>
 <game gamecode="3701895577">
  <general>
   <startdate>2022-08-11 22:00:34</startdate>
   <players>
    <player dealer="0" name="Bierschiss67" seat="1" chips="€50" win="€0" bet="€0"/>
    <player dealer="0" name="AlanMeining" seat="3" chips="€51,13" win="€0" bet="€0"/>
    <player dealer="1" name="Back2Warcraft" seat="5" chips="€83,56" win="€8,73" bet="€4,25"/>
    <player dealer="0" name="InMaxBzKillendos" seat="6" chips="€89,24" win="€0" bet="€4,25"/>
    <player dealer="0" name="13373678" seat="8" chips="€53,59" win="€0" bet="€0,50"/>
    <player dealer="0" name="SteveBiko" seat="10" chips="€58,71" win="€0" bet="€0"/>
   </players>
  </general>
  <round no="0">
   <action type="1" sum="€0,25" player="InMaxBzKillendos" no="1"/>
   <action type="2" sum="€0,50" player="13373678" no="2"/>
  </round>
  <round no="1">
   <cards type="Pocket" player="SteveBiko">X X</cards>
   <action type="0" sum="€0" player="SteveBiko" no="3"/>
   <cards type="Pocket" player="Bierschiss67">X X</cards>
   <action type="0" sum="€0" player="Bierschiss67" no="4"/>
   <cards type="Pocket" player="AlanMeining">X X</cards>
   <action type="0" sum="€0" player="AlanMeining" no="5"/>
   <cards type="Pocket" player="Back2Warcraft">D8 HQ</cards>
   <action type="23" sum="€1,25" player="Back2Warcraft" no="6"/>
   <cards type="Pocket" player="InMaxBzKillendos">D10 DK</cards>
   <action type="3" sum="€1" player="InMaxBzKillendos" no="7"/>
   <cards type="Pocket" player="13373678">D3 H5</cards>
   <action type="0" sum="€0" player="13373678" no="8"/>
  </round>
  <round no="2">
   <cards type="Flop">D2 CA S3</cards>
   <action type="4" sum="€0" player="InMaxBzKillendos" no="9"/>
   <action type="4" sum="€0" player="Back2Warcraft" no="10"/>
  </round>
  <round no="3">
   <cards type="Turn">DQ</cards>
   <action type="5" sum="€3" player="InMaxBzKillendos" no="11"/>
   <action type="3" sum="€3" player="Back2Warcraft" no="12"/>
  </round>
  <round no="4">
   <cards type="River">C10</cards>
   <action type="4" sum="€0" player="InMaxBzKillendos" no="13"/>
   <action type="4" sum="€0" player="Back2Warcraft" no="14"/>
  </round>
 </game>
 <game gamecode="3701895749">
  <general>
   <startdate>2022-08-11 22:01:40</startdate>
   <players>
    <player dealer="0" name="Bierschiss67" seat="1" chips="€50" win="€0" bet="€0"/>
    <player dealer="0" name="AlanMeining" seat="3" chips="€51,13" win="€0" bet="€0"/>
    <player dealer="0" name="Back2Warcraft" seat="5" chips="€88,04" win="€2,48" bet="€3,06"/>
    <player dealer="1" name="InMaxBzKillendos" seat="6" chips="€84,99" win="€0" bet="€0"/>
    <player dealer="0" name="13373678" seat="8" chips="€53,09" win="€0" bet="€0,25"/>
    <player dealer="0" name="SteveBiko" seat="10" chips="€58,71" win="€0" bet="€1,15"/>
   </players>
  </general>
  <round no="0">
   <action type="1" sum="€0,25" player="13373678" no="1"/>
   <action type="2" sum="€0,50" player="SteveBiko" no="2"/>
  </round>
  <round no="1">
   <cards type="Pocket" player="Bierschiss67">X X</cards>
   <action type="0" sum="€0" player="Bierschiss67" no="3"/>
   <cards type="Pocket" player="AlanMeining">X X</cards>
   <action type="0" sum="€0" player="AlanMeining" no="4"/>
   <cards type="Pocket" player="Back2Warcraft">X X</cards>
   <action type="23" sum="€1,15" player="Back2Warcraft" no="5"/>
   <cards type="Pocket" player="InMaxBzKillendos">X X</cards>
   <action type="0" sum="€0" player="InMaxBzKillendos" no="6"/>
   <cards type="Pocket" player="13373678">CJ H6</cards>
   <action type="0" sum="€0" player="13373678" no="7"/>
   <cards type="Pocket" player="SteveBiko">X X</cards>
   <action type="3" sum="€0,65" player="SteveBiko" no="8"/>
  </round>
  <round no="2">
   <cards type="Flop">DA CQ S2</cards>
   <action type="4" sum="€0" player="SteveBiko" no="9"/>
   <action type="5" sum="€1,91" player="Back2Warcraft" no="10"/>
   <action type="0" sum="€0" player="SteveBiko" no="11"/>
  </round>
 </game>
 <game gamecode="3701896956">
  <general>
   <startdate>2022-08-11 22:02:08</startdate>
   <players>
    <player dealer="0" name="Bierschiss67" seat="1" chips="€50" win="€0" bet="€0,50"/>
    <player dealer="0" name="AlanMeining" seat="3" chips="€51,13" win="€0" bet="€0"/>
    <player dealer="0" name="Back2Warcraft" seat="5" chips="€89,37" win="€0" bet="€1"/>
    <player dealer="0" name="InMaxBzKillendos" seat="6" chips="€84,99" win="€0" bet="€0"/>
    <player dealer="1" name="13373678" seat="8" chips="€52,84" win="€0" bet="€0"/>
    <player dealer="0" name="SteveBiko" seat="10" chips="€57,56" win="€2,50" bet="€6"/>
   </players>
  </general>
  <round no="0">
   <action type="1" sum="€0,25" player="SteveBiko" no="1"/>
   <action type="2" sum="€0,50" player="Bierschiss67" no="2"/>
  </round>
  <round no="1">
   <cards type="Pocket" player="AlanMeining">X X</cards>
   <action type="0" sum="€0" player="AlanMeining" no="3"/>
   <cards type="Pocket" player="Back2Warcraft">X X</cards>
   <action type="23" sum="€1" player="Back2Warcraft" no="4"/>
   <cards type="Pocket" player="InMaxBzKillendos">X X</cards>
   <action type="0" sum="€0" player="InMaxBzKillendos" no="5"/>
   <cards type="Pocket" player="13373678">D6 D3</cards>
   <action type="0" sum="€0" player="13373678" no="6"/>
   <cards type="Pocket" player="SteveBiko">X X</cards>
   <action type="23" sum="€6" player="SteveBiko" no="7"/>
   <cards type="Pocket" player="Bierschiss67">X X</cards>
   <action type="0" sum="€0" player="Bierschiss67" no="8"/>
   <action type="0" sum="€0" player="Back2Warcraft" no="9"/>
  </round>
 </game>
 <game gamecode="3701897057">
  <general>
   <startdate>2022-08-11 22:02:46</startdate>
   <players>
    <player dealer="0" name="Bierschiss67" seat="1" chips="€50" win="€0" bet="€0,25"/>
    <player dealer="0" name="Back2Warcraft" seat="5" chips="€88,37" win="€0,50" bet="€0,50"/>
    <player dealer="0" name="InMaxBzKillendos" seat="6" chips="€84,99" win="€0" bet="€0"/>
    <player dealer="0" name="13373678" seat="8" chips="€52,84" win="€0" bet="€0"/>
    <player dealer="1" name="SteveBiko" seat="10" chips="€59,06" win="€0" bet="€0"/>
   </players>
  </general>
  <round no="0">
   <action type="1" sum="€0,25" player="Bierschiss67" no="1"/>
   <action type="2" sum="€0,50" player="Back2Warcraft" no="2"/>
  </round>
  <round no="1">
   <cards type="Pocket" player="Back2Warcraft">X X</cards>
   <cards type="Pocket" player="InMaxBzKillendos">X X</cards>
   <action type="0" sum="€0" player="InMaxBzKillendos" no="3"/>
   <cards type="Pocket" player="13373678">SK D7</cards>
   <action type="0" sum="€0" player="13373678" no="4"/>
   <cards type="Pocket" player="SteveBiko">X X</cards>
   <action type="0" sum="€0" player="SteveBiko" no="5"/>
   <cards type="Pocket" player="Bierschiss67">X X</cards>
   <action type="0" sum="€0" player="Bierschiss67" no="6"/>
  </round>
 </game>
 <game gamecode="3701897078">
  <general>
   <startdate>2022-08-11 22:02:58</startdate>
   <players>
    <player dealer="1" name="Bierschiss67" seat="1" chips="€50" win="€0" bet="€0"/>
    <player dealer="0" name="Back2Warcraft" seat="5" chips="€88,62" win="€0" bet="€0,25"/>
    <player dealer="0" name="InMaxBzKillendos" seat="6" chips="€84,99" win="€4,44" bet="€4,44"/>
    <player dealer="0" name="13373678" seat="8" chips="€52,84" win="€0" bet="€0"/>
    <player dealer="0" name="SteveBiko" seat="10" chips="€59,06" win="€0" bet="€2,16"/>
   </players>
  </general>
  <round no="0">
   <action type="1" sum="€0,25" player="Back2Warcraft" no="1"/>
   <action type="2" sum="€0,50" player="InMaxBzKillendos" no="2"/>
  </round>
  <round no="1">
   <cards type="Pocket" player="13373678">S7 H2</cards>
   <action type="0" sum="€0" player="13373678" no="3"/>
   <cards type="Pocket" player="SteveBiko">X X</cards>
   <action type="23" sum="€1,25" player="SteveBiko" no="4"/>
   <cards type="Pocket" player="Bierschiss67">X X</cards>
   <action type="0" sum="€0" player="Bierschiss67" no="5"/>
   <cards type="Pocket" player="Back2Warcraft">X X</cards>
   <action type="0" sum="€0" player="Back2Warcraft" no="6"/>
   <cards type="Pocket" player="InMaxBzKillendos">X X</cards>
   <action type="3" sum="€0,75" player="InMaxBzKillendos" no="7"/>
  </round>
  <round no="2">
   <cards type="Flop">D6 CJ HA</cards>
   <action type="4" sum="€0" player="InMaxBzKillendos" no="8"/>
   <action type="5" sum="€0,91" player="SteveBiko" no="9"/>
   <action type="3" sum="€0,91" player="InMaxBzKillendos" no="10"/>
  </round>
  <round no="3">
   <cards type="Turn">S3</cards>
   <action type="4" sum="€0" player="InMaxBzKillendos" no="11"/>
   <action type="4" sum="€0" player="SteveBiko" no="12"/>
  </round>
  <round no="4">
   <cards type="River">C2</cards>
   <action type="5" sum="€2,28" player="InMaxBzKillendos" no="13"/>
   <action type="0" sum="€0" player="SteveBiko" no="14"/>
  </round>
 </game>
 <game gamecode="3701897263">
  <general>
   <startdate>2022-08-11 22:04:08</startdate>
   <players>
    <player dealer="0" name="Bierschiss67" seat="1" chips="€50" win="€0" bet="€0"/>
    <player dealer="1" name="Back2Warcraft" seat="5" chips="€88,37" win="€0" bet="€0"/>
    <player dealer="0" name="InMaxBzKillendos" seat="6" chips="€87,27" win="€1" bet="€1"/>
    <player dealer="0" name="13373678" seat="8" chips="€52,84" win="€0" bet="€0,50"/>
    <player dealer="0" name="SteveBiko" seat="10" chips="€56,90" win="€0" bet="€0"/>
   </players>
  </general>
  <round no="0">
   <action type="1" sum="€0,25" player="InMaxBzKillendos" no="1"/>
   <action type="2" sum="€0,50" player="13373678" no="2"/>
  </round>
  <round no="1">
   <cards type="Pocket" player="SteveBiko">X X</cards>
   <action type="0" sum="€0" player="SteveBiko" no="3"/>
   <cards type="Pocket" player="Bierschiss67">X X</cards>
   <action type="0" sum="€0" player="Bierschiss67" no="4"/>
   <cards type="Pocket" player="Back2Warcraft">X X</cards>
   <action type="0" sum="€0" player="Back2Warcraft" no="5"/>
   <cards type="Pocket" player="InMaxBzKillendos">X X</cards>
   <action type="23" sum="€1" player="InMaxBzKillendos" no="6"/>
   <cards type="Pocket" player="13373678">S7 CJ</cards>
   <action type="0" sum="€0" player="13373678" no="7"/>
  </round>
 </game>
 <game gamecode="3701897307">
  <general>
   <startdate>2022-08-11 22:04:26</startdate>
   <players>
    <player dealer="0" name="Bierschiss67" seat="1" chips="€50" win="€0" bet="€0"/>
    <player dealer="0" name="Back2Warcraft" seat="5" chips="€88,37" win="€1,25" bet="€1,15"/>
    <player dealer="1" name="InMaxBzKillendos" seat="6" chips="€87,77" win="€0" bet="€0"/>
    <player dealer="0" name="13373678" seat="8" chips="€52,34" win="€0" bet="€0,25"/>
    <player dealer="0" name="SteveBiko" seat="10" chips="€56,90" win="€0" bet="€0,50"/>
   </players>
  </general>
  <round no="0">
   <action type="1" sum="€0,25" player="13373678" no="1"/>
   <action type="2" sum="€0,50" player="SteveBiko" no="2"/>
  </round>
  <round no="1">
   <cards type="Pocket" player="Bierschiss67">X X</cards>
   <action type="0" sum="€0" player="Bierschiss67" no="3"/>
   <cards type="Pocket" player="Back2Warcraft">X X</cards>
   <action type="23" sum="€1,15" player="Back2Warcraft" no="4"/>
   <cards type="Pocket" player="InMaxBzKillendos">X X</cards>
   <action type="0" sum="€0" player="InMaxBzKillendos" no="5"/>
   <cards type="Pocket" player="13373678">S9 D7</cards>
   <action type="0" sum="€0" player="13373678" no="6"/>
   <cards type="Pocket" player="SteveBiko">X X</cards>
   <action type="0" sum="€0" player="SteveBiko" no="7"/>
  </round>
 </game>
 <game gamecode="3701897368">
  <general>
   <startdate>2022-08-11 22:04:50</startdate>
   <players>
    <player dealer="0" name="Bierschiss67" seat="1" chips="€50" win="€0" bet="€0,50"/>
    <player dealer="0" name="Back2Warcraft" seat="5" chips="€89,12" win="€0" bet="€0"/>
    <player dealer="0" name="InMaxBzKillendos" seat="6" chips="€87,77" win="€0" bet="€0"/>
    <player dealer="1" name="13373678" seat="8" chips="€52,09" win="€0" bet="€1,25"/>
    <player dealer="0" name="SteveBiko" seat="10" chips="€56,40" win="€3" bet="€6"/>
   </players>
  </general>
  <round no="0">
   <action type="1" sum="€0,25" player="SteveBiko" no="1"/>
   <action type="2" sum="€0,50" player="Bierschiss67" no="2"/>
  </round>
  <round no="1">
   <cards type="Pocket" player="Back2Warcraft">X X</cards>
   <action type="0" sum="€0" player="Back2Warcraft" no="3"/>
   <cards type="Pocket" player="InMaxBzKillendos">X X</cards>
   <action type="0" sum="€0" player="InMaxBzKillendos" no="4"/>
   <cards type="Pocket" player="13373678">DJ S9</cards>
   <action type="23" sum="€1,25" player="13373678" no="5"/>
   <cards type="Pocket" player="SteveBiko">X X</cards>
   <action type="23" sum="€6" player="SteveBiko" no="6"/>
   <cards type="Pocket" player="Bierschiss67">X X</cards>
   <action type="0" sum="€0" player="Bierschiss67" no="7"/>
   <action type="0" sum="€0" player="13373678" no="8"/>
  </round>
 </game>
 <game gamecode="3701897437">
  <general>
   <startdate>2022-08-11 22:05:20</startdate>
   <players>
    <player dealer="0" name="Bierschiss67" seat="1" chips="€50" win="€0" bet="€0,25"/>
    <player dealer="0" name="1254879896" seat="3" chips="€50" win="€0,50" bet="€0,50"/>
    <player dealer="0" name="Back2Warcraft" seat="5" chips="€89,12" win="€0" bet="€0"/>
    <player dealer="0" name="InMaxBzKillendos" seat="6" chips="€87,77" win="€0" bet="€0"/>
    <player dealer="0" name="13373678" seat="8" chips="€50,84" win="€0" bet="€0"/>
    <player dealer="1" name="SteveBiko" seat="10" chips="€58,15" win="€0" bet="€0"/>
   </players>
  </general>
  <round no="0">
   <action type="1" sum="€0,25" player="Bierschiss67" no="1"/>
   <action type="2" sum="€0,50" player="1254879896" no="2"/>
  </round>
  <round no="1">
   <cards type="Pocket" player="1254879896">X X</cards>
   <cards type="Pocket" player="Back2Warcraft">X X</cards>
   <action type="0" sum="€0" player="Back2Warcraft" no="3"/>
   <cards type="Pocket" player="InMaxBzKillendos">X X</cards>
   <action type="0" sum="€0" player="InMaxBzKillendos" no="4"/>
   <cards type="Pocket" player="13373678">D3 H10</cards>
   <action type="0" sum="€0" player="13373678" no="5"/>
   <cards type="Pocket" player="SteveBiko">X X</cards>
   <action type="0" sum="€0" player="SteveBiko" no="6"/>
   <cards type="Pocket" player="Bierschiss67">X X</cards>
   <action type="0" sum="€0" player="Bierschiss67" no="7"/>
  </round>
 </game>
 <game gamecode="3701897461">
  <general>
   <startdate>2022-08-11 22:05:32</startdate>
   <players>
    <player dealer="1" name="Bierschiss67" seat="1" chips="€50" win="€0" bet="€0"/>
    <player dealer="0" name="1254879896" seat="3" chips="€50,25" win="€0" bet="€0,25"/>
    <player dealer="0" name="Back2Warcraft" seat="5" chips="€89,12" win="€2,67" bet="€4"/>
    <player dealer="0" name="InMaxBzKillendos" seat="6" chips="€87,77" win="€0" bet="€0"/>
    <player dealer="0" name="13373678" seat="8" chips="€50,84" win="€0" bet="€1,25"/>
    <player dealer="0" name="SteveBiko" seat="10" chips="€58,15" win="€0" bet="€0"/>
   </players>
  </general>
  <round no="0">
   <action type="1" sum="€0,25" player="1254879896" no="1"/>
   <action type="2" sum="€0,50" player="Back2Warcraft" no="2"/>
  </round>
  <round no="1">
   <cards type="Pocket" player="InMaxBzKillendos">X X</cards>
   <action type="0" sum="€0" player="InMaxBzKillendos" no="3"/>
   <cards type="Pocket" player="13373678">CQ SJ</cards>
   <action type="23" sum="€1,25" player="13373678" no="4"/>
   <cards type="Pocket" player="SteveBiko">X X</cards>
   <action type="0" sum="€0" player="SteveBiko" no="5"/>
   <cards type="Pocket" player="Bierschiss67">X X</cards>
   <action type="0" sum="€0" player="Bierschiss67" no="6"/>
   <cards type="Pocket" player="1254879896">X X</cards>
   <action type="0" sum="€0" player="1254879896" no="7"/>
   <cards type="Pocket" player="Back2Warcraft">X X</cards>
   <action type="3" sum="€0,75" player="Back2Warcraft" no="8"/>
  </round>
  <round no="2">
   <cards type="Flop">D3 S6 SA</cards>
   <action type="4" sum="€0" player="Back2Warcraft" no="9"/>
   <action type="4" sum="€0" player="13373678" no="10"/>
  </round>
  <round no="3">
   <cards type="Turn">D9</cards>
   <action type="5" sum="€2,75" player="Back2Warcraft" no="11"/>
   <action type="0" sum="€0" player="13373678" no="12"/>
  </round>
 </game>
 <game gamecode="3701897707">
  <general>
   <startdate>2022-08-11 22:06:09</startdate>
   <players>
    <player dealer="0" name="Bierschiss67" seat="1" chips="€50" win="€0" bet="€0"/>
    <player dealer="1" name="1254879896" seat="3" chips="€50" win="€0" bet="€0"/>
    <player dealer="0" name="Back2Warcraft" seat="5" chips="€90,54" win="€0" bet="€0,25"/>
    <player dealer="0" name="InMaxBzKillendos" seat="6" chips="€87,77" win="€0,50" bet="€0,50"/>
    <player dealer="0" name="13373678" seat="8" chips="€50" win="€0" bet="€0"/>
    <player dealer="0" name="SteveBiko" seat="10" chips="€58,15" win="€0" bet="€0"/>
   </players>
  </general>
  <round no="0">
   <action type="1" sum="€0,25" player="Back2Warcraft" no="1"/>
   <action type="2" sum="€0,50" player="InMaxBzKillendos" no="2"/>
  </round>
  <round no="1">
   <cards type="Pocket" player="InMaxBzKillendos">X X</cards>
   <cards type="Pocket" player="13373678">HA C7</cards>
   <action type="0" sum="€0" player="13373678" no="3"/>
   <cards type="Pocket" player="SteveBiko">X X</cards>
   <action type="0" sum="€0" player="SteveBiko" no="4"/>
   <cards type="Pocket" player="Bierschiss67">X X</cards>
   <action type="0" sum="€0" player="Bierschiss67" no="5"/>
   <cards type="Pocket" player="1254879896">X X</cards>
   <action type="0" sum="€0" player="1254879896" no="6"/>
   <cards type="Pocket" player="Back2Warcraft">X X</cards>
   <action type="0" sum="€0" player="Back2Warcraft" no="7"/>
  </round>
 </game>
 <game gamecode="3701897738">
  <general>
   <startdate>2022-08-11 22:06:19</startdate>
   <players>
    <player dealer="0" name="Bierschiss67" seat="1" chips="€50" win="€0" bet="€0"/>
    <player dealer="0" name="1254879896" seat="3" chips="€50" win="€19,16" bet="€16"/>
    <player dealer="1" name="Back2Warcraft" seat="5" chips="€90,29" win="€0" bet="€0"/>
    <player dealer="0" name="InMaxBzKillendos" seat="6" chips="€88,02" win="€0" bet="€0,25"/>
    <player dealer="0" name="13373678" seat="8" chips="€50" win="€0" bet="€9,75"/>
    <player dealer="0" name="SteveBiko" seat="10" chips="€58,15" win="€0" bet="€0"/>
   </players>
  </general>
  <round no="0">
   <action type="1" sum="€0,25" player="InMaxBzKillendos" no="1"/>
   <action type="2" sum="€0,50" player="13373678" no="2"/>
  </round>
  <round no="1">
   <cards type="Pocket" player="SteveBiko">X X</cards>
   <action type="0" sum="€0" player="SteveBiko" no="3"/>
   <cards type="Pocket" player="Bierschiss67">X X</cards>
   <action type="0" sum="€0" player="Bierschiss67" no="4"/>
   <cards type="Pocket" player="1254879896">X X</cards>
   <action type="23" sum="€1,50" player="1254879896" no="5"/>
   <cards type="Pocket" player="Back2Warcraft">X X</cards>
   <action type="0" sum="€0" player="Back2Warcraft" no="6"/>
   <cards type="Pocket" player="InMaxBzKillendos">X X</cards>
   <action type="0" sum="€0" player="InMaxBzKillendos" no="7"/>
   <cards type="Pocket" player="13373678">HA D8</cards>
   <action type="3" sum="€1" player="13373678" no="8"/>
  </round>
  <round no="2">
   <cards type="Flop">D7 S4 S8</cards>
   <action type="4" sum="€0" player="13373678" no="9"/>
   <action type="5" sum="€2,50" player="1254879896" no="10"/>
   <action type="3" sum="€2,50" player="13373678" no="11"/>
  </round>
  <round no="3">
   <cards type="Turn">DK</cards>
   <action type="4" sum="€0" player="13373678" no="12"/>
   <action type="5" sum="€5,75" player="1254879896" no="13"/>
   <action type="3" sum="€5,75" player="13373678" no="14"/>
  </round>
  <round no="4">
   <cards type="River">SK</cards>
   <action type="4" sum="€0" player="13373678" no="15"/>
   <action type="5" sum="€6,25" player="1254879896" no="16"/>
   <action type="0" sum="€0" player="13373678" no="17"/>
  </round>
 </game>
 <game gamecode="3701897971">
  <general>
   <startdate>2022-08-11 22:07:38</startdate>
   <players>
    <player dealer="0" name="Bierschiss67" seat="1" chips="€50" win="€1,25" bet="€1,22"/>
    <player dealer="0" name="1254879896" seat="3" chips="€59,41" win="€0" bet="€0"/>
    <player dealer="0" name="Back2Warcraft" seat="5" chips="€90,29" win="€0" bet="€0"/>
    <player dealer="1" name="InMaxBzKillendos" seat="6" chips="€87,77" win="€0" bet="€0"/>
    <player dealer="0" name="13373678" seat="8" chips="€50" win="€0" bet="€0,25"/>
    <player dealer="0" name="SteveBiko" seat="10" chips="€58,15" win="€0" bet="€0,50"/>
   </players>
  </general>
  <round no="0">
   <action type="1" sum="€0,25" player="13373678" no="1"/>
   <action type="2" sum="€0,50" player="SteveBiko" no="2"/>
  </round>
  <round no="1">
   <cards type="Pocket" player="Bierschiss67">X X</cards>
   <action type="23" sum="€1,22" player="Bierschiss67" no="3"/>
   <cards type="Pocket" player="1254879896">X X</cards>
   <action type="0" sum="€0" player="1254879896" no="4"/>
   <cards type="Pocket" player="Back2Warcraft">X X</cards>
   <action type="0" sum="€0" player="Back2Warcraft" no="5"/>
   <cards type="Pocket" player="InMaxBzKillendos">X X</cards>
   <action type="0" sum="€0" player="InMaxBzKillendos" no="6"/>
   <cards type="Pocket" player="13373678">S2 C8</cards>
   <action type="0" sum="€0" player="13373678" no="7"/>
   <cards type="Pocket" player="SteveBiko">X X</cards>
   <action type="0" sum="€0" player="SteveBiko" no="8"/>
  </round>
 </game>
 <game gamecode="3701898016">
  <general>
   <startdate>2022-08-11 22:07:55</startdate>
   <players>
    <player dealer="0" name="Bierschiss67" seat="1" chips="€50,75" win="€0" bet="€0,50"/>
    <player dealer="0" name="1254879896" seat="3" chips="€59,41" win="€0" bet="€0"/>
    <player dealer="0" name="Back2Warcraft" seat="5" chips="€90,29" win="€0" bet="€0"/>
    <player dealer="0" name="InMaxBzKillendos" seat="6" chips="€87,77" win="€0" bet="€0"/>
    <player dealer="1" name="13373678" seat="8" chips="€50" win="€1,25" bet="€1,25"/>
    <player dealer="0" name="SteveBiko" seat="10" chips="€57,65" win="€0" bet="€0,25"/>
   </players>
  </general>
  <round no="0">
   <action type="1" sum="€0,25" player="SteveBiko" no="1"/>
   <action type="2" sum="€0,50" player="Bierschiss67" no="2"/>
  </round>
  <round no="1">
   <cards type="Pocket" player="1254879896">X X</cards>
   <action type="0" sum="€0" player="1254879896" no="3"/>
   <cards type="Pocket" player="Back2Warcraft">X X</cards>
   <action type="0" sum="€0" player="Back2Warcraft" no="4"/>
   <cards type="Pocket" player="InMaxBzKillendos">X X</cards>
   <action type="0" sum="€0" player="InMaxBzKillendos" no="5"/>
   <cards type="Pocket" player="13373678">C2 CJ</cards>
   <action type="23" sum="€1,25" player="13373678" no="6"/>
   <cards type="Pocket" player="SteveBiko">X X</cards>
   <action type="0" sum="€0" player="SteveBiko" no="7"/>
   <cards type="Pocket" player="Bierschiss67">X X</cards>
   <action type="0" sum="€0" player="Bierschiss67" no="8"/>
  </round>
 </game>
 <game gamecode="3701898059">
  <general>
   <startdate>2022-08-11 22:08:09</startdate>
   <players>
    <player dealer="0" name="Bierschiss67" seat="1" chips="€50,25" win="€0" bet="€0,25"/>
    <player dealer="0" name="1254879896" seat="3" chips="€59,41" win="€0" bet="€0,50"/>
    <player dealer="0" name="Back2Warcraft" seat="5" chips="€90,29" win="€0" bet="€0"/>
    <player dealer="0" name="InMaxBzKillendos" seat="6" chips="€87,77" win="€0" bet="€0"/>
    <player dealer="0" name="13373678" seat="8" chips="€50,75" win="€0" bet="€0"/>
    <player dealer="1" name="SteveBiko" seat="10" chips="€57,40" win="€1,25" bet="€1,25"/>
   </players>
  </general>
  <round no="0">
   <action type="1" sum="€0,25" player="Bierschiss67" no="1"/>
   <action type="2" sum="€0,50" player="1254879896" no="2"/>
  </round>
  <round no="1">
   <cards type="Pocket" player="Back2Warcraft">X X</cards>
   <action type="0" sum="€0" player="Back2Warcraft" no="3"/>
   <cards type="Pocket" player="InMaxBzKillendos">X X</cards>
   <action type="0" sum="€0" player="InMaxBzKillendos" no="4"/>
   <cards type="Pocket" player="13373678">H5 D8</cards>
   <action type="0" sum="€0" player="13373678" no="5"/>
   <cards type="Pocket" player="SteveBiko">X X</cards>
   <action type="23" sum="€1,25" player="SteveBiko" no="6"/>
   <cards type="Pocket" player="Bierschiss67">X X</cards>
   <action type="0" sum="€0" player="Bierschiss67" no="7"/>
   <cards type="Pocket" player="1254879896">X X</cards>
   <action type="0" sum="€0" player="1254879896" no="8"/>
  </round>
 </game>
 <game gamecode="3701898117">
  <general>
   <startdate>2022-08-11 22:08:32</startdate>
   <players>
    <player dealer="1" name="Bierschiss67" seat="1" chips="€50" win="€0" bet="€0"/>
    <player dealer="0" name="1254879896" seat="3" chips="€58,91" win="€0" bet="€0,25"/>
    <player dealer="0" name="Back2Warcraft" seat="5" chips="€90,29" win="€0" bet="€3"/>
    <player dealer="0" name="InMaxBzKillendos" seat="6" chips="€87,77" win="€6,07" bet="€3"/>
    <player dealer="0" name="13373678" seat="8" chips="€50,75" win="€0" bet="€0"/>
    <player dealer="0" name="SteveBiko" seat="10" chips="€58,15" win="€0" bet="€0"/>
   </players>
  </general>
  <round no="0">
   <action type="1" sum="€0,25" player="1254879896" no="1"/>
   <action type="2" sum="€0,50" player="Back2Warcraft" no="2"/>
  </round>
  <round no="1">
   <cards type="Pocket" player="InMaxBzKillendos">DA S8</cards>
   <action type="3" sum="€0,50" player="InMaxBzKillendos" no="3"/>
   <cards type="Pocket" player="13373678">D7 C9</cards>
   <action type="0" sum="€0" player="13373678" no="4"/>
   <cards type="Pocket" player="SteveBiko">X X</cards>
   <action type="0" sum="€0" player="SteveBiko" no="5"/>
   <cards type="Pocket" player="Bierschiss67">X X</cards>
   <action type="0" sum="€0" player="Bierschiss67" no="6"/>
   <cards type="Pocket" player="1254879896">X X</cards>
   <action type="0" sum="€0" player="1254879896" no="7"/>
   <cards type="Pocket" player="Back2Warcraft">H7 C6</cards>
   <action type="4" sum="€0" player="Back2Warcraft" no="8"/>
  </round>
  <round no="2">
   <cards type="Flop">SQ D5 CA</cards>
   <action type="4" sum="€0" player="Back2Warcraft" no="9"/>
   <action type="4" sum="€0" player="InMaxBzKillendos" no="10"/>
  </round>
  <round no="3">
   <cards type="Turn">S4</cards>
   <action type="5" sum="€1,25" player="Back2Warcraft" no="11"/>
   <action type="23" sum="€2,50" player="InMaxBzKillendos" no="12"/>
   <action type="3" sum="€1,25" player="Back2Warcraft" no="13"/>
  </round>
  <round no="4">
   <cards type="River">C7</cards>
   <action type="4" sum="€0" player="Back2Warcraft" no="14"/>
   <action type="4" sum="€0" player="InMaxBzKillendos" no="15"/>
  </round>
 </game>
 <game gamecode="3701898209">
  <general>
   <startdate>2022-08-11 22:09:05</startdate>
   <players>
    <player dealer="0" name="Bierschiss67" seat="1" chips="€50" win="€0" bet="€3,83"/>
    <player dealer="1" name="1254879896" seat="3" chips="€58,66" win="€0" bet="€0"/>
    <player dealer="0" name="Back2Warcraft" seat="5" chips="€87,29" win="€0" bet="€0,25"/>
    <player dealer="0" name="InMaxBzKillendos" seat="6" chips="€90,84" win="€0" bet="€0,50"/>
    <player dealer="0" name="13373678" seat="8" chips="€50,75" win="€0" bet="€0"/>
    <player dealer="0" name="SteveBiko" seat="10" chips="€58,15" win="€8,41" bet="€12,66"/>
   </players>
  </general>
  <round no="0">
   <action type="1" sum="€0,25" player="Back2Warcraft" no="1"/>
   <action type="2" sum="€0,50" player="InMaxBzKillendos" no="2"/>
  </round>
  <round no="1">
   <cards type="Pocket" player="13373678">C5 H8</cards>
   <action type="0" sum="€0" player="13373678" no="3"/>
   <cards type="Pocket" player="SteveBiko">X X</cards>
   <action type="23" sum="€1" player="SteveBiko" no="4"/>
   <cards type="Pocket" player="Bierschiss67">X X</cards>
   <action type="23" sum="€3,83" player="Bierschiss67" no="5"/>
   <cards type="Pocket" player="1254879896">X X</cards>
   <action type="0" sum="€0" player="1254879896" no="6"/>
   <cards type="Pocket" player="Back2Warcraft">X X</cards>
   <action type="0" sum="€0" player="Back2Warcraft" no="7"/>
   <cards type="Pocket" player="InMaxBzKillendos">X X</cards>
   <action type="0" sum="€0" player="InMaxBzKillendos" no="8"/>
   <action type="23" sum="€12,66" player="SteveBiko" no="9"/>
   <action type="0" sum="€0" player="Bierschiss67" no="10"/>
  </round>
 </game>
 <game gamecode="3701898308">
  <general>
   <startdate>2022-08-11 22:09:39</startdate>
   <players>
    <player dealer="0" name="Bierschiss67" seat="1" chips="€50" win="€0" bet="€0"/>
    <player dealer="0" name="1254879896" seat="3" chips="€58,66" win="€1,25" bet="€1,50"/>
    <player dealer="1" name="Back2Warcraft" seat="5" chips="€87,04" win="€0" bet="€0"/>
    <player dealer="0" name="InMaxBzKillendos" seat="6" chips="€90,34" win="€0" bet="€0,25"/>
    <player dealer="0" name="13373678" seat="8" chips="€50,75" win="€0" bet="€0,50"/>
    <player dealer="0" name="SteveBiko" seat="10" chips="€62,73" win="€0" bet="€0"/>
   </players>
  </general>
  <round no="0">
   <action type="1" sum="€0,25" player="InMaxBzKillendos" no="1"/>
   <action type="2" sum="€0,50" player="13373678" no="2"/>
  </round>
  <round no="1">
   <cards type="Pocket" player="SteveBiko">X X</cards>
   <action type="0" sum="€0" player="SteveBiko" no="3"/>
   <cards type="Pocket" player="Bierschiss67">X X</cards>
   <action type="0" sum="€0" player="Bierschiss67" no="4"/>
   <cards type="Pocket" player="1254879896">X X</cards>
   <action type="23" sum="€1,50" player="1254879896" no="5"/>
   <cards type="Pocket" player="Back2Warcraft">X X</cards>
   <action type="0" sum="€0" player="Back2Warcraft" no="6"/>
   <cards type="Pocket" player="InMaxBzKillendos">X X</cards>
   <action type="0" sum="€0" player="InMaxBzKillendos" no="7"/>
   <cards type="Pocket" player="13373678">C3 CK</cards>
   <action type="0" sum="€0" player="13373678" no="8"/>
  </round>
 </game>
 <game gamecode="3701898388">
  <general>
   <startdate>2022-08-11 22:10:08</startdate>
   <players>
    <player dealer="0" name="Bierschiss67" seat="1" chips="€50" win="€0" bet="€0"/>
    <player dealer="0" name="1254879896" seat="3" chips="€59,41" win="€0" bet="€0"/>
    <player dealer="0" name="Back2Warcraft" seat="5" chips="€87,04" win="€0" bet="€0"/>
    <player dealer="1" name="InMaxBzKillendos" seat="6" chips="€90,09" win="€0" bet="€0"/>
    <player dealer="0" name="13373678" seat="8" chips="€50,25" win="€1" bet="€1,50"/>
    <player dealer="0" name="SteveBiko" seat="10" chips="€62,73" win="€0" bet="€0,50"/>
   </players>
  </general>
  <round no="0">
   <action type="1" sum="€0,25" player="13373678" no="1"/>
   <action type="2" sum="€0,50" player="SteveBiko" no="2"/>
  </round>
  <round no="1">
   <cards type="Pocket" player="Bierschiss67">X X</cards>
   <action type="0" sum="€0" player="Bierschiss67" no="3"/>
   <cards type="Pocket" player="1254879896">X X</cards>
   <action type="0" sum="€0" player="1254879896" no="4"/>
   <cards type="Pocket" player="Back2Warcraft">X X</cards>
   <action type="0" sum="€0" player="Back2Warcraft" no="5"/>
   <cards type="Pocket" player="InMaxBzKillendos">X X</cards>
   <action type="0" sum="€0" player="InMaxBzKillendos" no="6"/>
   <cards type="Pocket" player="13373678">DQ D7</cards>
   <action type="23" sum="€1,50" player="13373678" no="7"/>
   <cards type="Pocket" player="SteveBiko">X X</cards>
   <action type="0" sum="€0" player="SteveBiko" no="8"/>
  </round>
 </game>
 <game gamecode="3701898448">
  <general>
   <startdate>2022-08-11 22:10:32</startdate>
   <players>
    <player dealer="0" name="Bierschiss67" seat="1" chips="€50" win="€0" bet="€0,50"/>
    <player dealer="0" name="1254879896" seat="3" chips="€59,41" win="€0" bet="€0"/>
    <player dealer="0" name="Back2Warcraft" seat="5" chips="€87,04" win="€0" bet="€0"/>
    <player dealer="0" name="InMaxBzKillendos" seat="6" chips="€90,09" win="€2,91" bet="€2,75"/>
    <player dealer="1" name="13373678" seat="8" chips="€50,75" win="€0" bet="€0"/>
    <player dealer="0" name="SteveBiko" seat="10" chips="€62,23" win="€2,91" bet="€2,75"/>
   </players>
  </general>
  <round no="0">
   <action type="1" sum="€0,25" player="SteveBiko" no="1"/>
   <action type="2" sum="€0,50" player="Bierschiss67" no="2"/>
  </round>
  <round no="1">
   <cards type="Pocket" player="1254879896">X X</cards>
   <action type="0" sum="€0" player="1254879896" no="3"/>
   <cards type="Pocket" player="Back2Warcraft">X X</cards>
   <action type="0" sum="€0" player="Back2Warcraft" no="4"/>
   <cards type="Pocket" player="InMaxBzKillendos">H9 HJ</cards>
   <action type="3" sum="€0,50" player="InMaxBzKillendos" no="5"/>
   <cards type="Pocket" player="13373678">S8 C4</cards>
   <action type="0" sum="€0" player="13373678" no="6"/>
   <cards type="Pocket" player="SteveBiko">D9 DJ</cards>
   <action type="3" sum="€0,25" player="SteveBiko" no="7"/>
   <cards type="Pocket" player="Bierschiss67">X X</cards>
   <action type="4" sum="€0" player="Bierschiss67" no="8"/>
  </round>
  <round no="2">
   <cards type="Flop">D10 C6 H3</cards>
   <action type="4" sum="€0" player="SteveBiko" no="9"/>
   <action type="4" sum="€0" player="Bierschiss67" no="10"/>
   <action type="4" sum="€0" player="InMaxBzKillendos" no="11"/>
  </round>
  <round no="3">
   <cards type="Turn">S9</cards>
   <action type="5" sum="€0,75" player="SteveBiko" no="12"/>
   <action type="0" sum="€0" player="Bierschiss67" no="13"/>
   <action type="3" sum="€0,75" player="InMaxBzKillendos" no="14"/>
  </round>
  <round no="4">
   <cards type="River">D3</cards>
   <action type="5" sum="€1,50" player="SteveBiko" no="15"/>
   <action type="3" sum="€1,50" player="InMaxBzKillendos" no="16"/>
  </round>
 </game>
 <game gamecode="3701898593">
  <general>
   <startdate>2022-08-11 22:11:23</startdate>
   <players>
    <player dealer="0" name="Bierschiss67" seat="1" chips="€50" win="€0" bet="€0,25"/>
    <player dealer="0" name="1254879896" seat="3" chips="€59,41" win="€0" bet="€0,50"/>
    <player dealer="0" name="Back2Warcraft" seat="5" chips="€87,04" win="€0" bet="€0"/>
    <player dealer="0" name="InMaxBzKillendos" seat="6" chips="€90,25" win="€1,25" bet="€1"/>
    <player dealer="0" name="13373678" seat="8" chips="€50,75" win="€0" bet="€0"/>
    <player dealer="1" name="SteveBiko" seat="10" chips="€62,39" win="€0" bet="€0"/>
   </players>
  </general>
  <round no="0">
   <action type="1" sum="€0,25" player="Bierschiss67" no="1"/>
   <action type="2" sum="€0,50" player="1254879896" no="2"/>
  </round>
  <round no="1">
   <cards type="Pocket" player="Back2Warcraft">X X</cards>
   <action type="0" sum="€0" player="Back2Warcraft" no="3"/>
   <cards type="Pocket" player="InMaxBzKillendos">X X</cards>
   <action type="23" sum="€1" player="InMaxBzKillendos" no="4"/>
   <cards type="Pocket" player="13373678">H5 S4</cards>
   <action type="0" sum="€0" player="13373678" no="5"/>
   <cards type="Pocket" player="SteveBiko">X X</cards>
   <action type="0" sum="€0" player="SteveBiko" no="6"/>
   <cards type="Pocket" player="Bierschiss67">X X</cards>
   <action type="0" sum="€0" player="Bierschiss67" no="7"/>
   <cards type="Pocket" player="1254879896">X X</cards>
   <action type="0" sum="€0" player="1254879896" no="8"/>
  </round>
 </game>
 <game gamecode="3701898652">
  <general>
   <startdate>2022-08-11 22:11:42</startdate>
   <players>
    <player dealer="1" name="Bierschiss67" seat="1" chips="€50" win="€0" bet="€0"/>
    <player dealer="0" name="1254879896" seat="3" chips="€58,91" win="€0" bet="€3,75"/>
    <player dealer="0" name="Back2Warcraft" seat="5" chips="€87,04" win="€7,28" bet="€9,37"/>
    <player dealer="0" name="InMaxBzKillendos" seat="6" chips="€91" win="€0" bet="€0"/>
    <player dealer="0" name="13373678" seat="8" chips="€50,75" win="€0" bet="€0"/>
    <player dealer="0" name="SteveBiko" seat="10" chips="€62,39" win="€0" bet="€0"/>
   </players>
  </general>
  <round no="0">
   <action type="1" sum="€0,25" player="1254879896" no="1"/>
   <action type="2" sum="€0,50" player="Back2Warcraft" no="2"/>
  </round>
  <round no="1">
   <cards type="Pocket" player="InMaxBzKillendos">X X</cards>
   <action type="0" sum="€0" player="InMaxBzKillendos" no="3"/>
   <cards type="Pocket" player="13373678">H4 H8</cards>
   <action type="0" sum="€0" player="13373678" no="4"/>
   <cards type="Pocket" player="SteveBiko">X X</cards>
   <action type="0" sum="€0" player="SteveBiko" no="5"/>
   <cards type="Pocket" player="Bierschiss67">X X</cards>
   <action type="0" sum="€0" player="Bierschiss67" no="6"/>
   <cards type="Pocket" player="1254879896">X X</cards>
   <action type="23" sum="€1,50" player="1254879896" no="7"/>
   <cards type="Pocket" player="Back2Warcraft">X X</cards>
   <action type="3" sum="€1" player="Back2Warcraft" no="8"/>
  </round>
  <round no="2">
   <cards type="Flop">S7 S8 D5</cards>
   <action type="4" sum="€0" player="1254879896" no="9"/>
   <action type="4" sum="€0" player="Back2Warcraft" no="10"/>
  </round>
  <round no="3">
   <cards type="Turn">SQ</cards>
   <action type="4" sum="€0" player="1254879896" no="11"/>
   <action type="5" sum="€2,25" player="Back2Warcraft" no="12"/>
   <action type="3" sum="€2,25" player="1254879896" no="13"/>
  </round>
  <round no="4">
   <cards type="River">H7</cards>
   <action type="4" sum="€0" player="1254879896" no="14"/>
   <action type="5" sum="€5,62" player="Back2Warcraft" no="15"/>
   <action type="0" sum="€0" player="1254879896" no="16"/>
  </round>
 </game>
 <game gamecode="3701900557">
  <general>
   <startdate>2022-08-11 22:12:56</startdate>
   <players>
    <player dealer="0" name="Bierschiss67" seat="1" chips="€50" win="€0" bet="€0"/>
    <player dealer="1" name="1254879896" seat="3" chips="€55,16" win="€0" bet="€0"/>
    <player dealer="0" name="Back2Warcraft" seat="5" chips="€90,57" win="€1" bet="€1,50"/>
    <player dealer="0" name="InMaxBzKillendos" seat="6" chips="€91" win="€0" bet="€0,50"/>
    <player dealer="0" name="13373678" seat="8" chips="€50,75" win="€0" bet="€0"/>
    <player dealer="0" name="SteveBiko" seat="10" chips="€62,39" win="€0" bet="€0"/>
   </players>
  </general>
  <round no="0">
   <action type="1" sum="€0,25" player="Back2Warcraft" no="1"/>
   <action type="2" sum="€0,50" player="InMaxBzKillendos" no="2"/>
  </round>
  <round no="1">
   <cards type="Pocket" player="13373678">HQ S2</cards>
   <action type="0" sum="€0" player="13373678" no="3"/>
   <cards type="Pocket" player="SteveBiko">X X</cards>
   <action type="0" sum="€0" player="SteveBiko" no="4"/>
   <cards type="Pocket" player="Bierschiss67">X X</cards>
   <action type="0" sum="€0" player="Bierschiss67" no="5"/>
   <cards type="Pocket" player="1254879896">X X</cards>
   <action type="0" sum="€0" player="1254879896" no="6"/>
   <cards type="Pocket" player="Back2Warcraft">X X</cards>
   <action type="23" sum="€1,50" player="Back2Warcraft" no="7"/>
   <cards type="Pocket" player="InMaxBzKillendos">X X</cards>
   <action type="0" sum="€0" player="InMaxBzKillendos" no="8"/>
  </round>
 </game>
 <game gamecode="3701900593">
  <general>
   <startdate>2022-08-11 22:13:08</startdate>
   <players>
    <player dealer="0" name="Bierschiss67" seat="1" chips="€50" win="€0" bet="€0"/>
    <player dealer="0" name="1254879896" seat="3" chips="€55,16" win="€8,48" bet="€5,62"/>
    <player dealer="1" name="Back2Warcraft" seat="5" chips="€91,07" win="€0" bet="€0"/>
    <player dealer="0" name="InMaxBzKillendos" seat="6" chips="€90,50" win="€0" bet="€4,12"/>
    <player dealer="0" name="13373678" seat="8" chips="€50,75" win="€0" bet="€0,50"/>
    <player dealer="0" name="SteveBiko" seat="10" chips="€62,39" win="€0" bet="€0"/>
   </players>
  </general>
  <round no="0">
   <action type="1" sum="€0,25" player="InMaxBzKillendos" no="1"/>
   <action type="2" sum="€0,50" player="13373678" no="2"/>
  </round>
  <round no="1">
   <cards type="Pocket" player="SteveBiko">X X</cards>
   <action type="0" sum="€0" player="SteveBiko" no="3"/>
   <cards type="Pocket" player="Bierschiss67">X X</cards>
   <action type="0" sum="€0" player="Bierschiss67" no="4"/>
   <cards type="Pocket" player="1254879896">X X</cards>
   <action type="23" sum="€1,50" player="1254879896" no="5"/>
   <cards type="Pocket" player="Back2Warcraft">X X</cards>
   <action type="0" sum="€0" player="Back2Warcraft" no="6"/>
   <cards type="Pocket" player="InMaxBzKillendos">X X</cards>
   <action type="3" sum="€1,25" player="InMaxBzKillendos" no="7"/>
   <cards type="Pocket" player="13373678">S8 HJ</cards>
   <action type="0" sum="€0" player="13373678" no="8"/>
  </round>
  <round no="2">
   <cards type="Flop">CJ H5 D8</cards>
   <action type="4" sum="€0" player="InMaxBzKillendos" no="9"/>
   <action type="5" sum="€1,12" player="1254879896" no="10"/>
   <action type="3" sum="€1,12" player="InMaxBzKillendos" no="11"/>
  </round>
  <round no="3">
   <cards type="Turn">D9</cards>
   <action type="4" sum="€0" player="InMaxBzKillendos" no="12"/>
   <action type="4" sum="€0" player="1254879896" no="13"/>
  </round>
  <round no="4">
   <cards type="River">C6</cards>
   <action type="5" sum="€1,50" player="InMaxBzKillendos" no="14"/>
   <action type="23" sum="€3" player="1254879896" no="15"/>
   <action type="0" sum="€0" player="InMaxBzKillendos" no="16"/>
  </round>
 </game>
 <game gamecode="3701900748">
  <general>
   <startdate>2022-08-11 22:14:08</startdate>
   <players>
    <player dealer="0" name="Bierschiss67" seat="1" chips="€50" win="€0" bet="€0"/>
    <player dealer="0" name="1254879896" seat="3" chips="€59,52" win="€0" bet="€0"/>
    <player dealer="0" name="Back2Warcraft" seat="5" chips="€91,07" win="€0" bet="€0"/>
    <player dealer="1" name="InMaxBzKillendos" seat="6" chips="€86,38" win="€0" bet="€0,50"/>
    <player dealer="0" name="13373678" seat="8" chips="€50,25" win="€1,50" bet="€2,50"/>
    <player dealer="0" name="SteveBiko" seat="10" chips="€62,39" win="€0" bet="€0,50"/>
   </players>
  </general>
  <round no="0">
   <action type="1" sum="€0,25" player="13373678" no="1"/>
   <action type="2" sum="€0,50" player="SteveBiko" no="2"/>
  </round>
  <round no="1">
   <cards type="Pocket" player="Bierschiss67">X X</cards>
   <action type="0" sum="€0" player="Bierschiss67" no="3"/>
   <cards type="Pocket" player="1254879896">X X</cards>
   <action type="0" sum="€0" player="1254879896" no="4"/>
   <cards type="Pocket" player="Back2Warcraft">X X</cards>
   <action type="0" sum="€0" player="Back2Warcraft" no="5"/>
   <cards type="Pocket" player="InMaxBzKillendos">X X</cards>
   <action type="3" sum="€0,50" player="InMaxBzKillendos" no="6"/>
   <cards type="Pocket" player="13373678">C9 H10</cards>
   <action type="23" sum="€2,50" player="13373678" no="7"/>
   <cards type="Pocket" player="SteveBiko">X X</cards>
   <action type="0" sum="€0" player="SteveBiko" no="8"/>
   <action type="0" sum="€0" player="InMaxBzKillendos" no="9"/>
  </round>
 </game>
 <game gamecode="3701900979">
  <general>
   <startdate>2022-08-11 22:14:43</startdate>
   <players>
    <player dealer="0" name="Bierschiss67" seat="1" chips="€50" win="€0,50" bet="€0,50"/>
    <player dealer="0" name="1254879896" seat="3" chips="€59,52" win="€0" bet="€0"/>
    <player dealer="0" name="Back2Warcraft" seat="5" chips="€91,07" win="€0" bet="€0"/>
    <player dealer="0" name="InMaxBzKillendos" seat="6" chips="€85,88" win="€0" bet="€0"/>
    <player dealer="1" name="13373678" seat="8" chips="€51,25" win="€0" bet="€0"/>
    <player dealer="0" name="SteveBiko" seat="10" chips="€61,89" win="€0" bet="€0,25"/>
   </players>
  </general>
  <round no="0">
   <action type="1" sum="€0,25" player="SteveBiko" no="1"/>
   <action type="2" sum="€0,50" player="Bierschiss67" no="2"/>
  </round>
  <round no="1">
   <cards type="Pocket" player="Bierschiss67">X X</cards>
   <cards type="Pocket" player="1254879896">X X</cards>
   <action type="0" sum="€0" player="1254879896" no="3"/>
   <cards type="Pocket" player="Back2Warcraft">X X</cards>
   <action type="0" sum="€0" player="Back2Warcraft" no="4"/>
   <cards type="Pocket" player="InMaxBzKillendos">X X</cards>
   <action type="0" sum="€0" player="InMaxBzKillendos" no="5"/>
   <cards type="Pocket" player="13373678">DJ H3</cards>
   <action type="0" sum="€0" player="13373678" no="6"/>
   <cards type="Pocket" player="SteveBiko">X X</cards>
   <action type="0" sum="€0" player="SteveBiko" no="7"/>
  </round>
 </game>
 <game gamecode="3701901002">
  <general>
   <startdate>2022-08-11 22:14:54</startdate>
   <players>
    <player dealer="0" name="Bierschiss67" seat="1" chips="€50,25" win="€0" bet="€0,25"/>
    <player dealer="0" name="1254879896" seat="3" chips="€59,52" win="€0,50" bet="€0,50"/>
    <player dealer="0" name="Back2Warcraft" seat="5" chips="€91,07" win="€0" bet="€0"/>
    <player dealer="0" name="InMaxBzKillendos" seat="6" chips="€85,88" win="€0" bet="€0"/>
    <player dealer="0" name="13373678" seat="8" chips="€51,25" win="€0" bet="€0"/>
    <player dealer="1" name="SteveBiko" seat="10" chips="€61,64" win="€0" bet="€0"/>
   </players>
  </general>
  <round no="0">
   <action type="1" sum="€0,25" player="Bierschiss67" no="1"/>
   <action type="2" sum="€0,50" player="1254879896" no="2"/>
  </round>
  <round no="1">
   <cards type="Pocket" player="1254879896">X X</cards>
   <cards type="Pocket" player="Back2Warcraft">X X</cards>
   <action type="0" sum="€0" player="Back2Warcraft" no="3"/>
   <cards type="Pocket" player="InMaxBzKillendos">X X</cards>
   <action type="0" sum="€0" player="InMaxBzKillendos" no="4"/>
   <cards type="Pocket" player="13373678">H2 CQ</cards>
   <action type="0" sum="€0" player="13373678" no="5"/>
   <cards type="Pocket" player="SteveBiko">X X</cards>
   <action type="0" sum="€0" player="SteveBiko" no="6"/>
   <cards type="Pocket" player="Bierschiss67">X X</cards>
   <action type="0" sum="€0" player="Bierschiss67" no="7"/>
  </round>
 </game>
 <game gamecode="3701901062">
  <general>
   <startdate>2022-08-11 22:15:21</startdate>
   <players>
    <player dealer="1" name="Bierschiss67" seat="1" chips="€50" win="€0" bet="€0"/>
    <player dealer="0" name="1254879896" seat="3" chips="€59,77" win="€0" bet="€0,25"/>
    <player dealer="0" name="Back2Warcraft" seat="5" chips="€91,07" win="€0" bet="€0,50"/>
    <player dealer="0" name="InMaxBzKillendos" seat="6" chips="€85,88" win="€0" bet="€0"/>
    <player dealer="0" name="13373678" seat="8" chips="€51,25" win="€1,25" bet="€1,25"/>
    <player dealer="0" name="SteveBiko" seat="10" chips="€61,64" win="€0" bet="€0"/>
   </players>
  </general>
  <round no="0">
   <action type="1" sum="€0,25" player="1254879896" no="1"/>
   <action type="2" sum="€0,50" player="Back2Warcraft" no="2"/>
  </round>
  <round no="1">
   <cards type="Pocket" player="InMaxBzKillendos">X X</cards>
   <action type="0" sum="€0" player="InMaxBzKillendos" no="3"/>
   <cards type="Pocket" player="13373678">SA HQ</cards>
   <action type="23" sum="€1,25" player="13373678" no="4"/>
   <cards type="Pocket" player="SteveBiko">X X</cards>
   <action type="0" sum="€0" player="SteveBiko" no="5"/>
   <cards type="Pocket" player="Bierschiss67">X X</cards>
   <action type="0" sum="€0" player="Bierschiss67" no="6"/>
   <cards type="Pocket" player="1254879896">X X</cards>
   <action type="0" sum="€0" player="1254879896" no="7"/>
   <cards type="Pocket" player="Back2Warcraft">X X</cards>
   <action type="0" sum="€0" player="Back2Warcraft" no="8"/>
  </round>
 </game>
 <game gamecode="3701901106">
  <general>
   <startdate>2022-08-11 22:15:38</startdate>
   <players>
    <player dealer="0" name="Bierschiss67" seat="1" chips="€50" win="€0" bet="€0"/>
    <player dealer="1" name="1254879896" seat="3" chips="€59,52" win="€0" bet="€0"/>
    <player dealer="0" name="Back2Warcraft" seat="5" chips="€90,57" win="€0" bet="€0,25"/>
    <player dealer="0" name="InMaxBzKillendos" seat="6" chips="€85,88" win="€0" bet="€0,50"/>
    <player dealer="0" name="13373678" seat="8" chips="€52" win="€1,25" bet="€1,25"/>
    <player dealer="0" name="SteveBiko" seat="10" chips="€61,64" win="€0" bet="€0"/>
   </players>
  </general>
  <round no="0">
   <action type="1" sum="€0,25" player="Back2Warcraft" no="1"/>
   <action type="2" sum="€0,50" player="InMaxBzKillendos" no="2"/>
  </round>
  <round no="1">
   <cards type="Pocket" player="13373678">HK DQ</cards>
   <action type="23" sum="€1,25" player="13373678" no="3"/>
   <cards type="Pocket" player="SteveBiko">X X</cards>
   <action type="0" sum="€0" player="SteveBiko" no="4"/>
   <cards type="Pocket" player="Bierschiss67">X X</cards>
   <action type="0" sum="€0" player="Bierschiss67" no="5"/>
   <cards type="Pocket" player="1254879896">X X</cards>
   <action type="0" sum="€0" player="1254879896" no="6"/>
   <cards type="Pocket" player="Back2Warcraft">X X</cards>
   <action type="0" sum="€0" player="Back2Warcraft" no="7"/>
   <cards type="Pocket" player="InMaxBzKillendos">X X</cards>
   <action type="0" sum="€0" player="InMaxBzKillendos" no="8"/>
  </round>
 </game>
 <game gamecode="3701901151">
  <general>
   <startdate>2022-08-11 22:15:54</startdate>
   <players>
    <player dealer="0" name="Bierschiss67" seat="1" chips="€50" win="€0" bet="€0"/>
    <player dealer="0" name="1254879896" seat="3" chips="€59,52" win="€10,92" bet="€5,38"/>
    <player dealer="1" name="Back2Warcraft" seat="5" chips="€90,32" win="€0" bet="€0"/>
    <player dealer="0" name="InMaxBzKillendos" seat="6" chips="€85,38" win="€0" bet="€5,38"/>
    <player dealer="0" name="13373678" seat="8" chips="€52,75" win="€0" bet="€0,50"/>
    <player dealer="0" name="SteveBiko" seat="10" chips="€61,64" win="€0" bet="€0"/>
   </players>
  </general>
  <round no="0">
   <action type="1" sum="€0,25" player="InMaxBzKillendos" no="1"/>
   <action type="2" sum="€0,50" player="13373678" no="2"/>
  </round>
  <round no="1">
   <cards type="Pocket" player="SteveBiko">X X</cards>
   <action type="0" sum="€0" player="SteveBiko" no="3"/>
   <cards type="Pocket" player="Bierschiss67">X X</cards>
   <action type="0" sum="€0" player="Bierschiss67" no="4"/>
   <cards type="Pocket" player="1254879896">H8 HQ</cards>
   <action type="23" sum="€1,50" player="1254879896" no="5"/>
   <cards type="Pocket" player="Back2Warcraft">X X</cards>
   <action type="0" sum="€0" player="Back2Warcraft" no="6"/>
   <cards type="Pocket" player="InMaxBzKillendos">SK SA</cards>
   <action type="3" sum="€1,25" player="InMaxBzKillendos" no="7"/>
   <cards type="Pocket" player="13373678">SJ C9</cards>
   <action type="0" sum="€0" player="13373678" no="8"/>
  </round>
  <round no="2">
   <cards type="Flop">D2 D10 SQ</cards>
   <action type="4" sum="€0" player="InMaxBzKillendos" no="9"/>
   <action type="5" sum="€1,94" player="1254879896" no="10"/>
   <action type="23" sum="€3,88" player="InMaxBzKillendos" no="11"/>
   <action type="3" sum="€1,94" player="1254879896" no="12"/>
  </round>
  <round no="3">
   <cards type="Turn">D6</cards>
   <action type="4" sum="€0" player="InMaxBzKillendos" no="13"/>
   <action type="4" sum="€0" player="1254879896" no="14"/>
  </round>
  <round no="4">
   <cards type="River">D7</cards>
   <action type="4" sum="€0" player="InMaxBzKillendos" no="15"/>
   <action type="4" sum="€0" player="1254879896" no="16"/>
  </round>
 </game>
 <game gamecode="3701901431">
  <general>
   <startdate>2022-08-11 22:17:39</startdate>
   <players>
    <player dealer="0" name="Bierschiss67" seat="1" chips="€50" win="€0" bet="€0"/>
    <player dealer="0" name="1254879896" seat="3" chips="€65,06" win="€0" bet="€0"/>
    <player dealer="0" name="Back2Warcraft" seat="5" chips="€90,32" win="€0" bet="€0"/>
    <player dealer="0" name="13373678" seat="8" chips="€52,25" win="€14,49" bet="€7,47"/>
    <player dealer="0" name="SteveBiko" seat="10" chips="€61,64" win="€0" bet="€7,47"/>
    <player dealer="1" name="InMaxBzKillendos" seat="6" chips="€80" win="€0" bet="€0"/>
   </players>
  </general>
  <round no="0">
   <action type="1" sum="€0,25" player="13373678" no="1"/>
   <action type="2" sum="€0,50" player="SteveBiko" no="2"/>
  </round>
  <round no="1">
   <cards type="Pocket" player="Bierschiss67">X X</cards>
   <action type="0" sum="€0" player="Bierschiss67" no="3"/>
   <cards type="Pocket" player="1254879896">X X</cards>
   <action type="0" sum="€0" player="1254879896" no="4"/>
   <cards type="Pocket" player="Back2Warcraft">X X</cards>
   <action type="0" sum="€0" player="Back2Warcraft" no="5"/>
   <cards type="Pocket" player="InMaxBzKillendos">X X</cards>
   <action type="0" sum="€0" player="InMaxBzKillendos" no="6"/>
   <cards type="Pocket" player="13373678">DA D4</cards>
   <action type="23" sum="€1,50" player="13373678" no="7"/>
   <cards type="Pocket" player="SteveBiko">HQ SQ</cards>
   <action type="23" sum="€4,50" player="SteveBiko" no="8"/>
   <action type="3" sum="€3" player="13373678" no="9"/>
  </round>
  <round no="2">
   <cards type="Flop">CA DK CK</cards>
   <action type="4" sum="€0" player="13373678" no="10"/>
   <action type="4" sum="€0" player="SteveBiko" no="11"/>
  </round>
  <round no="3">
   <cards type="Turn">H9</cards>
   <action type="4" sum="€0" player="13373678" no="12"/>
   <action type="4" sum="€0" player="SteveBiko" no="13"/>
  </round>
  <round no="4">
   <cards type="River">S8</cards>
   <action type="5" sum="€2,97" player="13373678" no="14"/>
   <action type="3" sum="€2,97" player="SteveBiko" no="15"/>
  </round>
 </game>
 <game gamecode="3701901565">
  <general>
   <startdate>2022-08-11 22:18:33</startdate>
   <players>
    <player dealer="0" name="Bierschiss67" seat="1" chips="€50" win="€13,30" bet="€6,73"/>
    <player dealer="0" name="1254879896" seat="3" chips="€65,06" win="€0" bet="€0"/>
    <player dealer="0" name="Back2Warcraft" seat="5" chips="€90,32" win="€0" bet="€0"/>
    <player dealer="1" name="13373678" seat="8" chips="€59,27" win="€0" bet="€6,73"/>
    <player dealer="0" name="SteveBiko" seat="10" chips="€54,17" win="€0" bet="€0,25"/>
   </players>
  </general>
  <round no="0">
   <action type="1" sum="€0,25" player="SteveBiko" no="1"/>
   <action type="2" sum="€0,50" player="Bierschiss67" no="2"/>
  </round>
  <round no="1">
   <cards type="Pocket" player="1254879896">X X</cards>
   <action type="0" sum="€0" player="1254879896" no="3"/>
   <cards type="Pocket" player="Back2Warcraft">X X</cards>
   <action type="0" sum="€0" player="Back2Warcraft" no="4"/>
   <cards type="Pocket" player="13373678">D5 H5</cards>
   <action type="23" sum="€1,25" player="13373678" no="5"/>
   <cards type="Pocket" player="SteveBiko">X X</cards>
   <action type="0" sum="€0" player="SteveBiko" no="6"/>
   <cards type="Pocket" player="Bierschiss67">D9 HK</cards>
   <action type="3" sum="€0,75" player="Bierschiss67" no="7"/>
  </round>
  <round no="2">
   <cards type="Flop">S9 CK DQ</cards>
   <action type="4" sum="€0" player="Bierschiss67" no="8"/>
   <action type="5" sum="€1,37" player="13373678" no="9"/>
   <action type="3" sum="€1,37" player="Bierschiss67" no="10"/>
  </round>
  <round no="3">
   <cards type="Turn">S4</cards>
   <action type="4" sum="€0" player="Bierschiss67" no="11"/>
   <action type="5" sum="€4,11" player="13373678" no="12"/>
   <action type="3" sum="€4,11" player="Bierschiss67" no="13"/>
  </round>
  <round no="4">
   <cards type="River">SK</cards>
   <action type="4" sum="€0" player="Bierschiss67" no="14"/>
   <action type="4" sum="€0" player="13373678" no="15"/>
  </round>
 </game>
 <game gamecode="3701901765">
  <general>
   <startdate>2022-08-11 22:20:00</startdate>
   <players>
    <player dealer="0" name="Bierschiss67" seat="1" chips="€56,57" win="€1" bet="€1,50"/>
    <player dealer="0" name="1254879896" seat="3" chips="€65,06" win="€0" bet="€0,50"/>
    <player dealer="0" name="Back2Warcraft" seat="5" chips="€90,32" win="€0" bet="€0"/>
    <player dealer="0" name="13373678" seat="8" chips="€52,54" win="€0" bet="€0"/>
    <player dealer="1" name="SteveBiko" seat="10" chips="€53,92" win="€0" bet="€0"/>
   </players>
  </general>
  <round no="0">
   <action type="1" sum="€0,25" player="Bierschiss67" no="1"/>
   <action type="2" sum="€0,50" player="1254879896" no="2"/>
  </round>
  <round no="1">
   <cards type="Pocket" player="Back2Warcraft">X X</cards>
   <action type="0" sum="€0" player="Back2Warcraft" no="3"/>
   <cards type="Pocket" player="13373678">S2 S5</cards>
   <action type="0" sum="€0" player="13373678" no="4"/>
   <cards type="Pocket" player="SteveBiko">X X</cards>
   <action type="0" sum="€0" player="SteveBiko" no="5"/>
   <cards type="Pocket" player="Bierschiss67">X X</cards>
   <action type="23" sum="€1,50" player="Bierschiss67" no="6"/>
   <cards type="Pocket" player="1254879896">X X</cards>
   <action type="0" sum="€0" player="1254879896" no="7"/>
  </round>
 </game>
 <game gamecode="3701901808">
  <general>
   <startdate>2022-08-11 22:20:16</startdate>
   <players>
    <player dealer="1" name="Bierschiss67" seat="1" chips="€57,07" win="€0" bet="€0"/>
    <player dealer="0" name="1254879896" seat="3" chips="€64,56" win="€1" bet="€1,50"/>
    <player dealer="0" name="Back2Warcraft" seat="5" chips="€90,32" win="€0" bet="€0,50"/>
    <player dealer="0" name="13373678" seat="8" chips="€52,54" win="€0" bet="€0"/>
    <player dealer="0" name="SteveBiko" seat="10" chips="€53,92" win="€0" bet="€0"/>
   </players>
  </general>
  <round no="0">
   <action type="1" sum="€0,25" player="1254879896" no="1"/>
   <action type="2" sum="€0,50" player="Back2Warcraft" no="2"/>
  </round>
  <round no="1">
   <cards type="Pocket" player="13373678">D3 H6</cards>
   <action type="0" sum="€0" player="13373678" no="3"/>
   <cards type="Pocket" player="SteveBiko">X X</cards>
   <action type="0" sum="€0" player="SteveBiko" no="4"/>
   <cards type="Pocket" player="Bierschiss67">X X</cards>
   <action type="0" sum="€0" player="Bierschiss67" no="5"/>
   <cards type="Pocket" player="1254879896">X X</cards>
   <action type="23" sum="€1,50" player="1254879896" no="6"/>
   <cards type="Pocket" player="Back2Warcraft">X X</cards>
   <action type="0" sum="€0" player="Back2Warcraft" no="7"/>
  </round>
 </game>
 <game gamecode="3701901862">
  <general>
   <startdate>2022-08-11 22:20:38</startdate>
   <players>
    <player dealer="0" name="Bierschiss67" seat="1" chips="€57,07" win="€0" bet="€0"/>
    <player dealer="1" name="1254879896" seat="3" chips="€65,06" win="€0" bet="€0"/>
    <player dealer="0" name="Back2Warcraft" seat="5" chips="€89,82" win="€0" bet="€4,50"/>
    <player dealer="0" name="13373678" seat="8" chips="€52,54" win="€8,73" bet="€9"/>
    <player dealer="0" name="SteveBiko" seat="10" chips="€53,92" win="€0" bet="€0"/>
   </players>
  </general>
  <round no="0">
   <action type="1" sum="€0,25" player="Back2Warcraft" no="1"/>
   <action type="2" sum="€0,50" player="13373678" no="2"/>
  </round>
  <round no="1">
   <cards type="Pocket" player="SteveBiko">X X</cards>
   <action type="0" sum="€0" player="SteveBiko" no="3"/>
   <cards type="Pocket" player="Bierschiss67">X X</cards>
   <action type="0" sum="€0" player="Bierschiss67" no="4"/>
   <cards type="Pocket" player="1254879896">X X</cards>
   <action type="0" sum="€0" player="1254879896" no="5"/>
   <cards type="Pocket" player="Back2Warcraft">X X</cards>
   <action type="23" sum="€1,50" player="Back2Warcraft" no="6"/>
   <cards type="Pocket" player="13373678">CQ SA</cards>
   <action type="23" sum="€4,50" player="13373678" no="7"/>
   <action type="3" sum="€3" player="Back2Warcraft" no="8"/>
  </round>
  <round no="2">
   <cards type="Flop">C4 HJ C10</cards>
   <action type="4" sum="€0" player="Back2Warcraft" no="9"/>
   <action type="5" sum="€4,50" player="13373678" no="10"/>
   <action type="0" sum="€0" player="Back2Warcraft" no="11"/>
  </round>
 </game>
 <game gamecode="3701902003">
  <general>
   <startdate>2022-08-11 22:21:17</startdate>
   <players>
    <player dealer="0" name="Bierschiss67" seat="1" chips="€57,07" win="€0" bet="€0"/>
    <player dealer="0" name="1254879896" seat="3" chips="€65,06" win="€0" bet="€0"/>
    <player dealer="1" name="Back2Warcraft" seat="5" chips="€85,32" win="€0" bet="€0"/>
    <player dealer="0" name="13373678" seat="8" chips="€56,77" win="€0" bet="€0,25"/>
    <player dealer="0" name="SteveBiko" seat="10" chips="€53,92" win="€0,50" bet="€0,50"/>
   </players>
  </general>
  <round no="0">
   <action type="1" sum="€0,25" player="13373678" no="1"/>
   <action type="2" sum="€0,50" player="SteveBiko" no="2"/>
  </round>
  <round no="1">
   <cards type="Pocket" player="SteveBiko">X X</cards>
   <cards type="Pocket" player="Bierschiss67">X X</cards>
   <action type="0" sum="€0" player="Bierschiss67" no="3"/>
   <cards type="Pocket" player="1254879896">X X</cards>
   <action type="0" sum="€0" player="1254879896" no="4"/>
   <cards type="Pocket" player="Back2Warcraft">X X</cards>
   <action type="0" sum="€0" player="Back2Warcraft" no="5"/>
   <cards type="Pocket" player="13373678">HJ S3</cards>
   <action type="0" sum="€0" player="13373678" no="6"/>
  </round>
 </game>
 <game gamecode="3701902043">
  <general>
   <startdate>2022-08-11 22:21:30</startdate>
   <players>
    <player dealer="0" name="Bierschiss67" seat="1" chips="€57,07" win="€0" bet="€0,50"/>
    <player dealer="0" name="1254879896" seat="3" chips="€65,06" win="€1,25" bet="€1,50"/>
    <player dealer="0" name="Back2Warcraft" seat="5" chips="€85,32" win="€0" bet="€0"/>
    <player dealer="1" name="13373678" seat="8" chips="€56,52" win="€0" bet="€0"/>
    <player dealer="0" name="SteveBiko" seat="10" chips="€54,17" win="€0" bet="€0,25"/>
   </players>
  </general>
  <round no="0">
   <action type="1" sum="€0,25" player="SteveBiko" no="1"/>
   <action type="2" sum="€0,50" player="Bierschiss67" no="2"/>
  </round>
  <round no="1">
   <cards type="Pocket" player="1254879896">X X</cards>
   <action type="23" sum="€1,50" player="1254879896" no="3"/>
   <cards type="Pocket" player="Back2Warcraft">X X</cards>
   <action type="0" sum="€0" player="Back2Warcraft" no="4"/>
   <cards type="Pocket" player="13373678">D4 C2</cards>
   <action type="0" sum="€0" player="13373678" no="5"/>
   <cards type="Pocket" player="SteveBiko">X X</cards>
   <action type="0" sum="€0" player="SteveBiko" no="6"/>
   <cards type="Pocket" player="Bierschiss67">X X</cards>
   <action type="0" sum="€0" player="Bierschiss67" no="7"/>
  </round>
 </game>
 <game gamecode="3701902075">
  <general>
   <startdate>2022-08-11 22:21:43</startdate>
   <players>
    <player dealer="0" name="Bierschiss67" seat="1" chips="€56,57" win="€0" bet="€0,25"/>
    <player dealer="0" name="1254879896" seat="3" chips="€65,81" win="€0" bet="€0,50"/>
    <player dealer="0" name="Back2Warcraft" seat="5" chips="€85,32" win="€1,25" bet="€1"/>
    <player dealer="0" name="13373678" seat="8" chips="€56,52" win="€0" bet="€0"/>
    <player dealer="1" name="SteveBiko" seat="10" chips="€53,92" win="€0" bet="€0"/>
   </players>
  </general>
  <round no="0">
   <action type="1" sum="€0,25" player="Bierschiss67" no="1"/>
   <action type="2" sum="€0,50" player="1254879896" no="2"/>
  </round>
  <round no="1">
   <cards type="Pocket" player="Back2Warcraft">X X</cards>
   <action type="23" sum="€1" player="Back2Warcraft" no="3"/>
   <cards type="Pocket" player="13373678">C10 H3</cards>
   <action type="0" sum="€0" player="13373678" no="4"/>
   <cards type="Pocket" player="SteveBiko">X X</cards>
   <action type="0" sum="€0" player="SteveBiko" no="5"/>
   <cards type="Pocket" player="Bierschiss67">X X</cards>
   <action type="0" sum="€0" player="Bierschiss67" no="6"/>
   <cards type="Pocket" player="1254879896">X X</cards>
   <action type="0" sum="€0" player="1254879896" no="7"/>
  </round>
 </game>
 <game gamecode="3701902138">
  <general>
   <startdate>2022-08-11 22:22:03</startdate>
   <players>
    <player dealer="1" name="Bierschiss67" seat="1" chips="€56,32" win="€1,25" bet="€1,22"/>
    <player dealer="0" name="1254879896" seat="3" chips="€65,31" win="€0" bet="€0,25"/>
    <player dealer="0" name="13373678" seat="8" chips="€56,52" win="€0" bet="€0,50"/>
    <player dealer="0" name="SteveBiko" seat="10" chips="€53,92" win="€0" bet="€0"/>
   </players>
  </general>
  <round no="0">
   <action type="1" sum="€0,25" player="1254879896" no="1"/>
   <action type="2" sum="€0,50" player="13373678" no="2"/>
  </round>
  <round no="1">
   <cards type="Pocket" player="SteveBiko">X X</cards>
   <action type="0" sum="€0" player="SteveBiko" no="3"/>
   <cards type="Pocket" player="Bierschiss67">X X</cards>
   <action type="23" sum="€1,22" player="Bierschiss67" no="4"/>
   <cards type="Pocket" player="1254879896">X X</cards>
   <action type="0" sum="€0" player="1254879896" no="5"/>
   <cards type="Pocket" player="13373678">H9 DJ</cards>
   <action type="0" sum="€0" player="13373678" no="6"/>
  </round>
 </game>
 <game gamecode="3701903834">
  <general>
   <startdate>2022-08-11 22:22:24</startdate>
   <players>
    <player dealer="0" name="Bierschiss67" seat="1" chips="€57,07" win="€0,50" bet="€0,50"/>
    <player dealer="1" name="1254879896" seat="3" chips="€65,06" win="€0" bet="€0"/>
    <player dealer="0" name="13373678" seat="8" chips="€56,02" win="€0" bet="€0,25"/>
   </players>
  </general>
  <round no="0">
   <action type="1" sum="€0,25" player="13373678" no="1"/>
   <action type="2" sum="€0,50" player="Bierschiss67" no="2"/>
  </round>
  <round no="1">
   <cards type="Pocket" player="Bierschiss67">X X</cards>
   <cards type="Pocket" player="1254879896">X X</cards>
   <action type="0" sum="€0" player="1254879896" no="3"/>
   <cards type="Pocket" player="13373678">HK C2</cards>
   <action type="0" sum="€0" player="13373678" no="4"/>
  </round>
 </game>
 <game gamecode="3701903859">
  <general>
   <startdate>2022-08-11 22:22:36</startdate>
   <players>
    <player dealer="0" name="Bierschiss67" seat="1" chips="€57,32" win="€1" bet="€1,50"/>
    <player dealer="0" name="1254879896" seat="3" chips="€65,06" win="€0" bet="€0,50"/>
    <player dealer="1" name="13373678" seat="8" chips="€55,77" win="€0" bet="€0"/>
   </players>
  </general>
  <round no="0">
   <action type="1" sum="€0,25" player="Bierschiss67" no="1"/>
   <action type="2" sum="€0,50" player="1254879896" no="2"/>
  </round>
  <round no="1">
   <cards type="Pocket" player="13373678">H10 C4</cards>
   <action type="0" sum="€0" player="13373678" no="3"/>
   <cards type="Pocket" player="Bierschiss67">X X</cards>
   <action type="23" sum="€1,50" player="Bierschiss67" no="4"/>
   <cards type="Pocket" player="1254879896">X X</cards>
   <action type="0" sum="€0" player="1254879896" no="5"/>
  </round>
 </game>
 <game gamecode="3701903917">
  <general>
   <startdate>2022-08-11 22:23:02</startdate>
   <players>
    <player dealer="1" name="Bierschiss67" seat="1" chips="€57,82" win="€1,25" bet="€1,22"/>
    <player dealer="0" name="1254879896" seat="3" chips="€64,56" win="€0" bet="€0,25"/>
    <player dealer="0" name="13373678" seat="8" chips="€55,77" win="€0" bet="€0,50"/>
   </players>
  </general>
  <round no="0">
   <action type="1" sum="€0,25" player="1254879896" no="1"/>
   <action type="2" sum="€0,50" player="13373678" no="2"/>
  </round>
  <round no="1">
   <cards type="Pocket" player="Bierschiss67">X X</cards>
   <action type="23" sum="€1,22" player="Bierschiss67" no="3"/>
   <cards type="Pocket" player="1254879896">X X</cards>
   <action type="0" sum="€0" player="1254879896" no="4"/>
   <cards type="Pocket" player="13373678">DJ S6</cards>
   <action type="0" sum="€0" player="13373678" no="5"/>
  </round>
 </game>
</session>
