<?xml version="1.0" encoding="utf-8"?>
<session sessioncode="4149022320">
 <general>
  <client_version>23.5.1.16</client_version>
  <mode>real</mode>
  <gametype>Holdem NL €0,25/€0,50</gametype>
  <tablename>100BB Salzburg 25, 492037641</tablename>
  <tablecurrency>EUR</tablecurrency>
  <smallblind>€0,25</smallblind>
  <bigblind>€0,50</bigblind>
  <duration>00:08:16</duration>
  <gamecount>15</gamecount>
  <startdate>2024-09-09 20:31:08</startdate>
  <currency>EUR</currency>
  <nickname>13373678</nickname>
  <bets>€18,25</bets>
  <wins>€4,50</wins>
  <chipsin>€38,50</chipsin>
  <chipsout>€51,25</chipsout>
  <statuspoints>0,00</statuspoints>
  <awardpoints>0,00</awardpoints>
  <ipoints>0,00</ipoints>
  <tablesize>6</tablesize>
 </general>
 <game gamecode="3927425689">
  <general>
   <startdate>2024-09-09 20:31:08</startdate>
   <players>
    <player chips="€75,58" name="Player 3" win="€0" seat="3" bet="€11,93" dealer="0"/>
    <player chips="€51,45" name="Player 5" win="€0" seat="5" bet="€0" dealer="1"/>
    <player chips="€62,95" name="Player 6" win="€23,63" seat="6" bet="€11,93" dealer="0"/>
    <player chips="€50" name="Player 8" win="€0" seat="8" bet="€0,50" dealer="0"/>
    <player chips="€60,22" name="Player 10" win="€0" seat="10" bet="€0" dealer="0"/>
   </players>
  </general>
  <round no="0">
   <action sum="€0,25" type="1" player="Player 6" no="1"/>
   <action sum="€0,50" type="2" player="Player 8" no="2"/>
  </round>
  <round no="1">
   <cards type="Pocket" player="Player 10">X X</cards>
   <action sum="€0" type="0" player="Player 10" no="3"/>
   <cards type="Pocket" player="Player 3">C10 CJ</cards>
   <action sum="€1,15" type="23" player="Player 3" no="4"/>
   <cards type="Pocket" player="Player 5">X X</cards>
   <action sum="€0" type="0" player="Player 5" no="5"/>
   <cards type="Pocket" player="Player 6">SQ CK</cards>
   <action sum="€0,90" type="3" player="Player 6" no="6"/>
   <cards type="Pocket" player="Player 8">X X</cards>
   <action sum="€0" type="0" player="Player 8" no="7"/>
  </round>
  <round no="2">
   <cards type="Flop">D9 DK C4</cards>
   <action sum="€0" type="4" player="Player 6" no="8"/>
   <action sum="€0,92" type="5" player="Player 3" no="9"/>
   <action sum="€0,92" type="3" player="Player 6" no="10"/>
  </round>
  <round no="3">
   <cards type="Turn">H2</cards>
   <action sum="€0" type="4" player="Player 6" no="11"/>
   <action sum="€3,48" type="5" player="Player 3" no="12"/>
   <action sum="€3,48" type="3" player="Player 6" no="13"/>
  </round>
  <round no="4">
   <cards type="River">H7</cards>
   <action sum="€0" type="4" player="Player 6" no="14"/>
   <action sum="€6,38" type="5" player="Player 3" no="15"/>
   <action sum="€6,38" type="3" player="Player 6" no="16"/>
  </round>
 </game>
 <game gamecode="3927426029">
  <general>
   <startdate>2024-09-09 20:32:47</startdate>
   <players>
    <player chips="€63,65" name="Player 3" win="€2,19" seat="3" bet="€1,74" dealer="0"/>
    <player chips="€51,45" name="Player 5" win="€0" seat="5" bet="€0" dealer="0"/>
    <player chips="€74,65" name="Player 6" win="€0" seat="6" bet="€0" dealer="1"/>
    <player chips="€50" name="Player 8" win="€0" seat="8" bet="€0,25" dealer="0"/>
    <player chips="€60,22" name="Player 10" win="€0" seat="10" bet="€1" dealer="0"/>
   </players>
  </general>
  <round no="0">
   <action sum="€0,25" type="1" player="Player 8" no="1"/>
   <action sum="€0,50" type="2" player="Player 10" no="2"/>
  </round>
  <round no="1">
   <cards type="Pocket" player="Player 3">X X</cards>
   <action sum="€1" type="23" player="Player 3" no="3"/>
   <cards type="Pocket" player="Player 5">X X</cards>
   <action sum="€0" type="0" player="Player 5" no="4"/>
   <cards type="Pocket" player="Player 6">X X</cards>
   <action sum="€0" type="0" player="Player 6" no="5"/>
   <cards type="Pocket" player="Player 8">X X</cards>
   <action sum="€0" type="0" player="Player 8" no="6"/>
   <cards type="Pocket" player="Player 10">X X</cards>
   <action sum="€0,50" type="3" player="Player 10" no="7"/>
  </round>
  <round no="2">
   <cards type="Flop">CK S8 SJ</cards>
   <action sum="€0" type="4" player="Player 10" no="8"/>
   <action sum="€0,74" type="5" player="Player 3" no="9"/>
   <action sum="€0" type="0" player="Player 10" no="10"/>
  </round>
 </game>
 <game gamecode="3927426107">
  <general>
   <startdate>2024-09-09 20:33:07</startdate>
   <players>
    <player chips="€50" name="13373678" win="€0" seat="1" bet="€11,50" dealer="0"/>
    <player chips="€64,84" name="raharatkaisee" win="€28,50" seat="3" bet="€64,84" dealer="0"/>
    <player chips="€51,45" name="135123265123" win="€0" seat="5" bet="€0" dealer="0"/>
    <player chips="€74,65" name="BlackRiverDrift" win="€0" seat="6" bet="€0" dealer="0"/>
    <player chips="€50" name="GRINSEKATZE" win="€0" seat="8" bet="€0" dealer="1"/>
    <player chips="€59,22" name="VarianzFranz" win="€0" seat="10" bet="€5,50" dealer="0"/>
   </players>
  </general>
  <round no="0">
   <action sum="€0,25" type="1" player="VarianzFranz" no="1"/>
   <action sum="€0,50" type="2" player="13373678" no="2"/>
  </round>
  <round no="1">
   <cards type="Pocket" player="raharatkaisee">X X</cards>
   <action sum="€1" type="23" player="raharatkaisee" no="3"/>
   <cards type="Pocket" player="135123265123">X X</cards>
   <action sum="€0" type="0" player="135123265123" no="4"/>
   <cards type="Pocket" player="BlackRiverDrift">X X</cards>
   <action sum="€0" type="0" player="BlackRiverDrift" no="5"/>
   <cards type="Pocket" player="GRINSEKATZE">X X</cards>
   <action sum="€0" type="0" player="GRINSEKATZE" no="6"/>
   <cards type="Pocket" player="VarianzFranz">X X</cards>
   <action sum="€5,50" type="23" player="VarianzFranz" no="7"/>
   <cards type="Pocket" player="13373678">S9 D9</cards>
   <action sum="€11,50" type="23" player="13373678" no="8"/>
   <action sum="€64,84" type="23" player="raharatkaisee" no="9"/>
   <action sum="€0" type="0" player="VarianzFranz" no="10"/>
   <action sum="€0" type="0" player="13373678" no="11"/>
  </round>
 </game>
 <game gamecode="3927426232">
  <general>
   <startdate>2024-09-09 20:33:47</startdate>
   <players>
    <player chips="€50" name="13373678" win="€1" seat="1" bet="€1,50" dealer="0"/>
    <player chips="€81,84" name="raharatkaisee" win="€0" seat="3" bet="€0,50" dealer="0"/>
    <player chips="€51,45" name="135123265123" win="€0" seat="5" bet="€0" dealer="0"/>
    <player chips="€74,65" name="BlackRiverDrift" win="€0" seat="6" bet="€0" dealer="0"/>
    <player chips="€50" name="GRINSEKATZE" win="€0" seat="8" bet="€0" dealer="0"/>
    <player chips="€53,72" name="VarianzFranz" win="€0" seat="10" bet="€0" dealer="1"/>
   </players>
  </general>
  <round no="0">
   <action sum="€0,25" type="1" player="13373678" no="1"/>
   <action sum="€0,50" type="2" player="raharatkaisee" no="2"/>
  </round>
  <round no="1">
   <cards type="Pocket" player="135123265123">X X</cards>
   <action sum="€0" type="0" player="135123265123" no="3"/>
   <cards type="Pocket" player="BlackRiverDrift">X X</cards>
   <action sum="€0" type="0" player="BlackRiverDrift" no="4"/>
   <cards type="Pocket" player="GRINSEKATZE">X X</cards>
   <action sum="€0" type="0" player="GRINSEKATZE" no="5"/>
   <cards type="Pocket" player="VarianzFranz">X X</cards>
   <action sum="€0" type="0" player="VarianzFranz" no="6"/>
   <cards type="Pocket" player="13373678">H10 C9</cards>
   <action sum="€1,50" type="23" player="13373678" no="7"/>
   <cards type="Pocket" player="raharatkaisee">X X</cards>
   <action sum="€0" type="0" player="raharatkaisee" no="8"/>
  </round>
 </game>
 <game gamecode="3927426284">
  <general>
   <startdate>2024-09-09 20:34:02</startdate>
   <players>
    <player chips="€50,50" name="13373678" win="€0" seat="1" bet="€0" dealer="1"/>
    <player chips="€81,34" name="raharatkaisee" win="€1" seat="3" bet="€1,50" dealer="0"/>
    <player chips="€51,45" name="135123265123" win="€0" seat="5" bet="€0,50" dealer="0"/>
    <player chips="€74,65" name="BlackRiverDrift" win="€0" seat="6" bet="€0" dealer="0"/>
    <player chips="€50" name="GRINSEKATZE" win="€0" seat="8" bet="€0" dealer="0"/>
    <player chips="€53,72" name="VarianzFranz" win="€0" seat="10" bet="€0" dealer="0"/>
   </players>
  </general>
  <round no="0">
   <action sum="€0,25" type="1" player="raharatkaisee" no="1"/>
   <action sum="€0,50" type="2" player="135123265123" no="2"/>
  </round>
  <round no="1">
   <cards type="Pocket" player="BlackRiverDrift">X X</cards>
   <action sum="€0" type="0" player="BlackRiverDrift" no="3"/>
   <cards type="Pocket" player="GRINSEKATZE">X X</cards>
   <action sum="€0" type="0" player="GRINSEKATZE" no="4"/>
   <cards type="Pocket" player="VarianzFranz">X X</cards>
   <action sum="€0" type="0" player="VarianzFranz" no="5"/>
   <cards type="Pocket" player="13373678">H2 C6</cards>
   <action sum="€0" type="0" player="13373678" no="6"/>
   <cards type="Pocket" player="raharatkaisee">X X</cards>
   <action sum="€1,50" type="23" player="raharatkaisee" no="7"/>
   <cards type="Pocket" player="135123265123">X X</cards>
   <action sum="€0" type="0" player="135123265123" no="8"/>
  </round>
 </game>
 <game gamecode="3927426373">
  <general>
   <startdate>2024-09-09 20:34:22</startdate>
   <players>
    <player chips="€50,50" name="13373678" win="€1,25" seat="1" bet="€1,25" dealer="0"/>
    <player chips="€81,84" name="raharatkaisee" win="€0" seat="3" bet="€0" dealer="1"/>
    <player chips="€50,95" name="135123265123" win="€0" seat="5" bet="€0,25" dealer="0"/>
    <player chips="€74,65" name="BlackRiverDrift" win="€0" seat="6" bet="€0,50" dealer="0"/>
    <player chips="€50" name="GRINSEKATZE" win="€0" seat="8" bet="€0" dealer="0"/>
    <player chips="€53,72" name="VarianzFranz" win="€0" seat="10" bet="€0" dealer="0"/>
   </players>
  </general>
  <round no="0">
   <action sum="€0,25" type="1" player="135123265123" no="1"/>
   <action sum="€0,50" type="2" player="BlackRiverDrift" no="2"/>
  </round>
  <round no="1">
   <cards type="Pocket" player="GRINSEKATZE">X X</cards>
   <action sum="€0" type="0" player="GRINSEKATZE" no="3"/>
   <cards type="Pocket" player="VarianzFranz">X X</cards>
   <action sum="€0" type="0" player="VarianzFranz" no="4"/>
   <cards type="Pocket" player="13373678">S6 SA</cards>
   <action sum="€1,25" type="23" player="13373678" no="5"/>
   <cards type="Pocket" player="raharatkaisee">X X</cards>
   <action sum="€0" type="0" player="raharatkaisee" no="6"/>
   <cards type="Pocket" player="135123265123">X X</cards>
   <action sum="€0" type="0" player="135123265123" no="7"/>
   <cards type="Pocket" player="BlackRiverDrift">X X</cards>
   <action sum="€0" type="0" player="BlackRiverDrift" no="8"/>
  </round>
 </game>
 <game gamecode="3927426500">
  <general>
   <startdate>2024-09-09 20:35:02</startdate>
   <players>
    <player chips="€51,25" name="13373678" win="€0" seat="1" bet="€0" dealer="0"/>
    <player chips="€81,84" name="raharatkaisee" win="€1,25" seat="3" bet="€1,15" dealer="0"/>
    <player chips="€50,70" name="135123265123" win="€0" seat="5" bet="€0" dealer="1"/>
    <player chips="€74,15" name="BlackRiverDrift" win="€0" seat="6" bet="€0,25" dealer="0"/>
    <player chips="€50" name="GRINSEKATZE" win="€0" seat="8" bet="€0,50" dealer="0"/>
    <player chips="€53,72" name="VarianzFranz" win="€0" seat="10" bet="€0" dealer="0"/>
   </players>
  </general>
  <round no="0">
   <action sum="€0,25" type="1" player="BlackRiverDrift" no="1"/>
   <action sum="€0,50" type="2" player="GRINSEKATZE" no="2"/>
  </round>
  <round no="1">
   <cards type="Pocket" player="VarianzFranz">X X</cards>
   <action sum="€0" type="0" player="VarianzFranz" no="3"/>
   <cards type="Pocket" player="13373678">HK D7</cards>
   <action sum="€0" type="0" player="13373678" no="4"/>
   <cards type="Pocket" player="raharatkaisee">X X</cards>
   <action sum="€1,15" type="23" player="raharatkaisee" no="5"/>
   <cards type="Pocket" player="135123265123">X X</cards>
   <action sum="€0" type="0" player="135123265123" no="6"/>
   <cards type="Pocket" player="BlackRiverDrift">X X</cards>
   <action sum="€0" type="0" player="BlackRiverDrift" no="7"/>
   <cards type="Pocket" player="GRINSEKATZE">X X</cards>
   <action sum="€0" type="0" player="GRINSEKATZE" no="8"/>
  </round>
 </game>
 <game gamecode="3927426599">
  <general>
   <startdate>2024-09-09 20:35:30</startdate>
   <players>
    <player chips="€51,25" name="13373678" win="€0" seat="1" bet="€0,50" dealer="0"/>
    <player chips="€82,59" name="raharatkaisee" win="€7,75" seat="3" bet="€10" dealer="0"/>
    <player chips="€50,70" name="135123265123" win="€0" seat="5" bet="€3,50" dealer="0"/>
    <player chips="€73,90" name="BlackRiverDrift" win="€0" seat="6" bet="€0" dealer="1"/>
    <player chips="€50" name="GRINSEKATZE" win="€0" seat="8" bet="€0,25" dealer="0"/>
   </players>
  </general>
  <round no="0">
   <action sum="€0,25" type="1" player="GRINSEKATZE" no="1"/>
   <action sum="€0,50" type="2" player="13373678" no="2"/>
  </round>
  <round no="1">
   <cards type="Pocket" player="raharatkaisee">X X</cards>
   <action sum="€1" type="23" player="raharatkaisee" no="3"/>
   <cards type="Pocket" player="135123265123">X X</cards>
   <action sum="€3,50" type="23" player="135123265123" no="4"/>
   <cards type="Pocket" player="BlackRiverDrift">X X</cards>
   <action sum="€0" type="0" player="BlackRiverDrift" no="5"/>
   <cards type="Pocket" player="GRINSEKATZE">X X</cards>
   <action sum="€0" type="0" player="GRINSEKATZE" no="6"/>
   <cards type="Pocket" player="13373678">H6 H2</cards>
   <action sum="€0" type="0" player="13373678" no="7"/>
   <action sum="€10" type="23" player="raharatkaisee" no="8"/>
   <action sum="€0" type="0" player="135123265123" no="9"/>
  </round>
 </game>
 <game gamecode="3927426702">
  <general>
   <startdate>2024-09-09 20:36:01</startdate>
   <players>
    <player chips="€50,75" name="13373678" win="€0" seat="1" bet="€0,25" dealer="0"/>
    <player chips="€86,84" name="raharatkaisee" win="€0" seat="3" bet="€0,50" dealer="0"/>
    <player chips="€73,90" name="BlackRiverDrift" win="€0" seat="6" bet="€0" dealer="0"/>
    <player chips="€50" name="GRINSEKATZE" win="€1,25" seat="8" bet="€1,25" dealer="1"/>
    <player chips="€50" name="135123265123" win="€0" seat="5" bet="€0" dealer="0"/>
   </players>
  </general>
  <round no="0">
   <action sum="€0,25" type="1" player="13373678" no="1"/>
   <action sum="€0,50" type="2" player="raharatkaisee" no="2"/>
  </round>
  <round no="1">
   <cards type="Pocket" player="135123265123">X X</cards>
   <action sum="€0" type="0" player="135123265123" no="3"/>
   <cards type="Pocket" player="BlackRiverDrift">X X</cards>
   <action sum="€0" type="0" player="BlackRiverDrift" no="4"/>
   <cards type="Pocket" player="GRINSEKATZE">X X</cards>
   <action sum="€1,25" type="23" player="GRINSEKATZE" no="5"/>
   <cards type="Pocket" player="13373678">D8 H10</cards>
   <action sum="€0" type="0" player="13373678" no="6"/>
   <cards type="Pocket" player="raharatkaisee">X X</cards>
   <action sum="€0" type="0" player="raharatkaisee" no="7"/>
  </round>
 </game>
 <game gamecode="3927426795">
  <general>
   <startdate>2024-09-09 20:36:29</startdate>
   <players>
    <player chips="€50,50" name="13373678" win="€1,25" seat="1" bet="€1,25" dealer="1"/>
    <player chips="€86,34" name="raharatkaisee" win="€0" seat="3" bet="€0,25" dealer="0"/>
    <player chips="€73,90" name="BlackRiverDrift" win="€0" seat="6" bet="€0,50" dealer="0"/>
    <player chips="€50,75" name="GRINSEKATZE" win="€0" seat="8" bet="€0" dealer="0"/>
   </players>
  </general>
  <round no="0">
   <action sum="€0,25" type="1" player="raharatkaisee" no="1"/>
   <action sum="€0,50" type="2" player="BlackRiverDrift" no="2"/>
  </round>
  <round no="1">
   <cards type="Pocket" player="GRINSEKATZE">X X</cards>
   <action sum="€0" type="0" player="GRINSEKATZE" no="3"/>
   <cards type="Pocket" player="13373678">H9 C6</cards>
   <action sum="€1,25" type="23" player="13373678" no="4"/>
   <cards type="Pocket" player="raharatkaisee">X X</cards>
   <action sum="€0" type="0" player="raharatkaisee" no="5"/>
   <cards type="Pocket" player="BlackRiverDrift">X X</cards>
   <action sum="€0" type="0" player="BlackRiverDrift" no="6"/>
  </round>
 </game>
 <game gamecode="3927428251">
  <general>
   <startdate>2024-09-09 20:36:43</startdate>
   <players>
    <player chips="€51,25" name="13373678" win="€0" seat="1" bet="€0" dealer="0"/>
    <player chips="€86,09" name="raharatkaisee" win="€1,25" seat="3" bet="€1,25" dealer="1"/>
    <player chips="€73,40" name="BlackRiverDrift" win="€0" seat="6" bet="€0,25" dealer="0"/>
    <player chips="€50,75" name="GRINSEKATZE" win="€0" seat="8" bet="€0,50" dealer="0"/>
   </players>
  </general>
  <round no="0">
   <action sum="€0,25" type="1" player="BlackRiverDrift" no="1"/>
   <action sum="€0,50" type="2" player="GRINSEKATZE" no="2"/>
  </round>
  <round no="1">
   <cards type="Pocket" player="13373678">S2 SQ</cards>
   <action sum="€0" type="0" player="13373678" no="3"/>
   <cards type="Pocket" player="raharatkaisee">X X</cards>
   <action sum="€1,25" type="23" player="raharatkaisee" no="4"/>
   <cards type="Pocket" player="BlackRiverDrift">X X</cards>
   <action sum="€0" type="0" player="BlackRiverDrift" no="5"/>
   <cards type="Pocket" player="GRINSEKATZE">X X</cards>
   <action sum="€0" type="0" player="GRINSEKATZE" no="6"/>
  </round>
 </game>
 <game gamecode="3927428323">
  <general>
   <startdate>2024-09-09 20:37:06</startdate>
   <players>
    <player chips="€51,25" name="13373678" win="€0" seat="1" bet="€0,50" dealer="0"/>
    <player chips="€86,84" name="raharatkaisee" win="€1,25" seat="3" bet="€1,15" dealer="0"/>
    <player chips="€73,15" name="BlackRiverDrift" win="€0" seat="6" bet="€0" dealer="1"/>
    <player chips="€50,25" name="GRINSEKATZE" win="€0" seat="8" bet="€0,25" dealer="0"/>
   </players>
  </general>
  <round no="0">
   <action sum="€0,25" type="1" player="GRINSEKATZE" no="1"/>
   <action sum="€0,50" type="2" player="13373678" no="2"/>
  </round>
  <round no="1">
   <cards type="Pocket" player="raharatkaisee">X X</cards>
   <action sum="€1,15" type="23" player="raharatkaisee" no="3"/>
   <cards type="Pocket" player="BlackRiverDrift">X X</cards>
   <action sum="€0" type="0" player="BlackRiverDrift" no="4"/>
   <cards type="Pocket" player="GRINSEKATZE">X X</cards>
   <action sum="€0" type="0" player="GRINSEKATZE" no="5"/>
   <cards type="Pocket" player="13373678">S8 C2</cards>
   <action sum="€0" type="0" player="13373678" no="6"/>
  </round>
 </game>
 <game gamecode="3927428405">
  <general>
   <startdate>2024-09-09 20:37:31</startdate>
   <players>
    <player chips="€50,75" name="13373678" win="€1" seat="1" bet="€1,50" dealer="0"/>
    <player chips="€87,59" name="raharatkaisee" win="€0" seat="3" bet="€0,50" dealer="0"/>
    <player chips="€73,15" name="BlackRiverDrift" win="€0" seat="6" bet="€0" dealer="0"/>
    <player chips="€50" name="GRINSEKATZE" win="€0" seat="8" bet="€0" dealer="1"/>
   </players>
  </general>
  <round no="0">
   <action sum="€0,25" type="1" player="13373678" no="1"/>
   <action sum="€0,50" type="2" player="raharatkaisee" no="2"/>
  </round>
  <round no="1">
   <cards type="Pocket" player="BlackRiverDrift">X X</cards>
   <action sum="€0" type="0" player="BlackRiverDrift" no="3"/>
   <cards type="Pocket" player="GRINSEKATZE">X X</cards>
   <action sum="€0" type="0" player="GRINSEKATZE" no="4"/>
   <cards type="Pocket" player="13373678">D10 D4</cards>
   <action sum="€1,50" type="23" player="13373678" no="5"/>
   <cards type="Pocket" player="raharatkaisee">X X</cards>
   <action sum="€0" type="0" player="raharatkaisee" no="6"/>
  </round>
 </game>
 <game gamecode="3927428654">
  <general>
   <startdate>2024-09-09 20:37:55</startdate>
   <players>
    <player chips="€51,25" name="13373678" win="€0" seat="1" bet="€0" dealer="1"/>
    <player chips="€87,09" name="raharatkaisee" win="€0" seat="3" bet="€0,25" dealer="0"/>
    <player chips="€73,15" name="BlackRiverDrift" win="€2,38" seat="6" bet="€3,08" dealer="0"/>
    <player chips="€50" name="GRINSEKATZE" win="€0" seat="8" bet="€1,10" dealer="0"/>
   </players>
  </general>
  <round no="0">
   <action sum="€0,25" type="1" player="raharatkaisee" no="1"/>
   <action sum="€0,50" type="2" player="BlackRiverDrift" no="2"/>
  </round>
  <round no="1">
   <cards type="Pocket" player="GRINSEKATZE">X X</cards>
   <action sum="€1,10" type="23" player="GRINSEKATZE" no="3"/>
   <cards type="Pocket" player="13373678">S8 HQ</cards>
   <action sum="€0" type="0" player="13373678" no="4"/>
   <cards type="Pocket" player="raharatkaisee">X X</cards>
   <action sum="€0" type="0" player="raharatkaisee" no="5"/>
   <cards type="Pocket" player="BlackRiverDrift">X X</cards>
   <action sum="€0,60" type="3" player="BlackRiverDrift" no="6"/>
  </round>
  <round no="2">
   <cards type="Flop">C10 H6 H8</cards>
   <action sum="€0" type="4" player="BlackRiverDrift" no="7"/>
   <action sum="€0" type="4" player="GRINSEKATZE" no="8"/>
  </round>
  <round no="3">
   <cards type="Turn">S3</cards>
   <action sum="€0" type="4" player="BlackRiverDrift" no="9"/>
   <action sum="€0" type="4" player="GRINSEKATZE" no="10"/>
  </round>
  <round no="4">
   <cards type="River">S2</cards>
   <action sum="€1,98" type="5" player="BlackRiverDrift" no="11"/>
   <action sum="€0" type="0" player="GRINSEKATZE" no="12"/>
  </round>
 </game>
 <game gamecode="3927429131">
  <general>
   <startdate>2024-09-09 20:39:11</startdate>
   <players>
    <player chips="€51,25" name="13373678" win="€0" seat="1" bet="€0" dealer="0"/>
    <player chips="€86,84" name="raharatkaisee" win="€0" seat="3" bet="€0" dealer="1"/>
    <player chips="€74,43" name="BlackRiverDrift" win="€0" seat="6" bet="€0,25" dealer="0"/>
    <player chips="€50" name="GRINSEKATZE" win="€0,50" seat="8" bet="€0,50" dealer="0"/>
   </players>
  </general>
  <round no="0">
   <action sum="€0,25" type="1" player="BlackRiverDrift" no="1"/>
   <action sum="€0,50" type="2" player="GRINSEKATZE" no="2"/>
  </round>
  <round no="1">
   <cards type="Pocket" player="GRINSEKATZE">X X</cards>
   <cards type="Pocket" player="13373678">DA C3</cards>
   <action sum="€0" type="0" player="13373678" no="3"/>
   <cards type="Pocket" player="raharatkaisee">X X</cards>
   <action sum="€0" type="0" player="raharatkaisee" no="4"/>
   <cards type="Pocket" player="BlackRiverDrift">X X</cards>
   <action sum="€0" type="0" player="BlackRiverDrift" no="5"/>
  </round>
 </game>
</session>
